{"institucion":"UNIVERSIDAD DE LA SERENA","fecha_corte":"2026-07-19","resumen":{"saldo_total":2729947105.0,"monto_transferido_total":4472714654.0,"rendido_total":1728195722.0,"porcentaje_rendido":38.6,"cuotas_con_deuda":80,"por_estado_morosidad":{"DEUDA MOROSA":22,"DEUDA SIN RETRASO":32,"DEUDA VENCIDA":26}},"proximos_vencimientos":[{"Subdirección":"REDES, ESTRATEGIA Y CONOCIMIENTO (SREC)","Programa":"PCI","Cuenta":"12106041200100","Nombre Cuenta":"INES ESTATALES","Imputacion":"3303","financiamiento":"ANID","Beneficiario":"UNIVERSIDAD DE LA SERENA","Público/Privado":"SI","Jurídico/Natural":"INSTITUCION PUBLICA","Proyecto":"INGE220009","etapa":"","Fecha de Transferencia":"2023-12-15","Numero de Cuota":"4","Monto de Transferencia":6316667.0,"Aplicaciones (Rendiciones)":6268332.0,"Reintegros":0.0,"Saldo":48335.0,"Presentación Rendición":"2026-01-15","Vigente/Pendiente (según Rendición presentada)":"PENDIENTE","Fecha Término de Proyecto":"2026-11-24","Estado según saldo (2 años del giro)":"DEUDA MOROSA"},{"Subdirección":"REDES, ESTRATEGIA Y CONOCIMIENTO (SREC)","Programa":"ASTRONOMIA","Cuenta":"11405270000000","Nombre Cuenta":"APLICACIÓN FONDOS GEMINI","Imputacion":"0","financiamiento":"Adm. Terceros","Beneficiario":"UNIVERSIDAD DE LA SERENA","Público/Privado":"SI","Jurídico/Natural":"INSTITUCION PUBLICA","Proyecto":"32230017","etapa":"","Fecha de Transferencia":"2024-06-13","Numero de Cuota":"C1-2","Monto de Transferencia":32148800.0,"Aplicaciones (Rendiciones)":29249949.0,"Reintegros":0.0,"Saldo":2898851.0,"Presentación Rendición":"2026-06-19","Vigente/Pendiente (según Rendición presentada)":"PENDIENTE","Fecha Término de Proyecto":"2026-05-22","Estado según saldo (2 años del giro)":"DEUDA MOROSA"},{"Subdirección":"REDES, ESTRATEGIA Y CONOCIMIENTO (SREC)","Programa":"ASTRONOMIA","Cuenta":"11405270000000","Nombre Cuenta":"APLICACIÓN FONDOS GEMINI","Imputacion":"0","financiamiento":"Adm. Terceros","Beneficiario":"UNIVERSIDAD DE LA SERENA","Público/Privado":"SI","Jurídico/Natural":"INSTITUCION PUBLICA","Proyecto":"32230017","etapa":"","Fecha de Transferencia":"2025-07-22","Numero de Cuota":"C2-2","Monto de Transferencia":32148800.0,"Aplicaciones (Rendiciones)":0.0,"Reintegros":0.0,"Saldo":32148800.0,"Presentación Rendición":"2026-06-22","Vigente/Pendiente (según Rendición presentada)":"PENDIENTE","Fecha Término de Proyecto":"2026-05-22","Estado según saldo (2 años del giro)":"DEUDA SIN RETRASO"}],"detalle":[{"Subdirección":"REDES, ESTRATEGIA Y CONOCIMIENTO (SREC)","Programa":"ASTRONOMIA","Cuenta":"11405260000000","Nombre Cuenta":"APLICACIÓN FONDOS ALMA","Imputacion":"0","financiamiento":"Adm. Terceros","Beneficiario":"UNIVERSIDAD DE LA SERENA","Público/Privado":"SI","Jurídico/Natural":"INSTITUCION PUBLICA","Proyecto":"31220036","etapa":"","Fecha de Transferencia":"2023-08-21","Numero de Cuota":"1","Monto de Transferencia":10600000.0,"Aplicaciones (Rendiciones)":0.0,"Reintegros":0.0,"Saldo":10600000.0,"Presentación Rendición":"8888-08-08","Vigente/Pendiente (según Rendición presentada)":"VIGENTE","Fecha Término de Proyecto":"2025-03-30","Estado según saldo (2 años del giro)":"DEUDA MOROSA"},{"Subdirección":"REDES, ESTRATEGIA Y CONOCIMIENTO (SREC)","Programa":"ASTRONOMIA","Cuenta":"11405260000000","Nombre Cuenta":"APLICACIÓN FONDOS ALMA","Imputacion":"0","financiamiento":"Adm. Terceros","Beneficiario":"UNIVERSIDAD DE LA SERENA","Público/Privado":"SI","Jurídico/Natural":"INSTITUCION PUBLICA","Proyecto":"31220036","etapa":"","Fecha de Transferencia":"2025-08-29","Numero de Cuota":"C2-2","Monto de Transferencia":10600000.0,"Aplicaciones (Rendiciones)":7467007.0,"Reintegros":0.0,"Saldo":3132993.0,"Presentación Rendición":"8888-08-08","Vigente/Pendiente (según Rendición presentada)":"VIGENTE","Fecha Término de Proyecto":"2025-09-30","Estado según saldo (2 años del giro)":"DEUDA SIN RETRASO"},{"Subdirección":"REDES, ESTRATEGIA Y CONOCIMIENTO (SREC)","Programa":"ASTRONOMIA","Cuenta":"11405260000000","Nombre Cuenta":"APLICACIÓN FONDOS ALMA","Imputacion":"0","financiamiento":"Adm. Terceros","Beneficiario":"UNIVERSIDAD DE LA SERENA","Público/Privado":"SI","Jurídico/Natural":"INSTITUCION PUBLICA","Proyecto":"31240052","etapa":"","Fecha de Transferencia":"2024-12-17","Numero de Cuota":"C1-2","Monto de Transferencia":34914000.0,"Aplicaciones (Rendiciones)":0.0,"Reintegros":0.0,"Saldo":34914000.0,"Presentación Rendición":"2026-12-22","Vigente/Pendiente (según Rendición presentada)":"VIGENTE","Fecha Término de Proyecto":"2026-11-29","Estado según saldo (2 años del giro)":"DEUDA VENCIDA"},{"Subdirección":"REDES, ESTRATEGIA Y CONOCIMIENTO (SREC)","Programa":"ASTRONOMIA","Cuenta":"11405260000000","Nombre Cuenta":"APLICACIÓN FONDOS ALMA","Imputacion":"0","financiamiento":"Adm. Terceros","Beneficiario":"UNIVERSIDAD DE LA SERENA","Público/Privado":"SI","Jurídico/Natural":"INSTITUCION PUBLICA","Proyecto":"ASTRO20-0041","etapa":"","Fecha de Transferencia":"2021-08-26","Numero de Cuota":"1","Monto de Transferencia":15000000.0,"Aplicaciones (Rendiciones)":0.0,"Reintegros":0.0,"Saldo":15000000.0,"Presentación Rendición":"8888-08-08","Vigente/Pendiente (según Rendición presentada)":"VIGENTE","Fecha Término de Proyecto":"2023-06-10","Estado según saldo (2 años del giro)":"DEUDA MOROSA"},{"Subdirección":"REDES, ESTRATEGIA Y CONOCIMIENTO (SREC)","Programa":"ASTRONOMIA","Cuenta":"11405270000000","Nombre Cuenta":"APLICACIÓN FONDOS GEMINI","Imputacion":"0","financiamiento":"Adm. Terceros","Beneficiario":"UNIVERSIDAD DE LA SERENA","Público/Privado":"SI","Jurídico/Natural":"INSTITUCION PUBLICA","Proyecto":"32230017","etapa":"","Fecha de Transferencia":"2025-07-22","Numero de Cuota":"C2-2","Monto de Transferencia":32148800.0,"Aplicaciones (Rendiciones)":0.0,"Reintegros":0.0,"Saldo":32148800.0,"Presentación Rendición":"2026-06-22","Vigente/Pendiente (según Rendición presentada)":"PENDIENTE","Fecha Término de Proyecto":"2026-05-22","Estado según saldo (2 años del giro)":"DEUDA SIN RETRASO"},{"Subdirección":"REDES, ESTRATEGIA Y CONOCIMIENTO (SREC)","Programa":"ASTRONOMIA","Cuenta":"11405270000000","Nombre Cuenta":"APLICACIÓN FONDOS GEMINI","Imputacion":"0","financiamiento":"Adm. Terceros","Beneficiario":"UNIVERSIDAD DE LA SERENA","Público/Privado":"SI","Jurídico/Natural":"INSTITUCION PUBLICA","Proyecto":"32230017","etapa":"","Fecha de Transferencia":"2024-06-13","Numero de Cuota":"C1-2","Monto de Transferencia":32148800.0,"Aplicaciones (Rendiciones)":29249949.0,"Reintegros":0.0,"Saldo":2898851.0,"Presentación Rendición":"2026-06-19","Vigente/Pendiente (según Rendición presentada)":"PENDIENTE","Fecha Término de Proyecto":"2026-05-22","Estado según saldo (2 años del giro)":"DEUDA MOROSA"},{"Subdirección":"REDES, ESTRATEGIA Y CONOCIMIENTO (SREC)","Programa":"ASTRONOMIA","Cuenta":"11405270000000","Nombre Cuenta":"APLICACIÓN FONDOS GEMINI","Imputacion":"0","financiamiento":"Adm. Terceros","Beneficiario":"UNIVERSIDAD DE LA SERENA","Público/Privado":"SI","Jurídico/Natural":"INSTITUCION PUBLICA","Proyecto":"32240021","etapa":"","Fecha de Transferencia":"2026-05-25","Numero de Cuota":"C2-2","Monto de Transferencia":34914000.0,"Aplicaciones (Rendiciones)":0.0,"Reintegros":0.0,"Saldo":34914000.0,"Presentación Rendición":"2027-01-21","Vigente/Pendiente (según Rendición presentada)":"VIGENTE","Fecha Término de Proyecto":"2026-12-04","Estado según saldo (2 años del giro)":"DEUDA SIN RETRASO"},{"Subdirección":"REDES, ESTRATEGIA Y CONOCIMIENTO (SREC)","Programa":"ASTRONOMIA","Cuenta":"11405270000000","Nombre Cuenta":"APLICACIÓN FONDOS GEMINI","Imputacion":"0","financiamiento":"Adm. Terceros","Beneficiario":"UNIVERSIDAD DE LA SERENA","Público/Privado":"SI","Jurídico/Natural":"INSTITUCION PUBLICA","Proyecto":"32240021","etapa":"","Fecha de Transferencia":"2024-12-17","Numero de Cuota":"C1-2","Monto de Transferencia":34914000.0,"Aplicaciones (Rendiciones)":0.0,"Reintegros":0.0,"Saldo":34914000.0,"Presentación Rendición":"2027-01-21","Vigente/Pendiente (según Rendición presentada)":"VIGENTE","Fecha Término de Proyecto":"2026-12-04","Estado según saldo (2 años del giro)":"DEUDA VENCIDA"},{"Subdirección":"REDES, ESTRATEGIA Y CONOCIMIENTO (SREC)","Programa":"ASTRONOMIA","Cuenta":"11405270000000","Nombre Cuenta":"APLICACIÓN FONDOS GEMINI","Imputacion":"0","financiamiento":"Adm. Terceros","Beneficiario":"UNIVERSIDAD DE LA SERENA","Público/Privado":"SI","Jurídico/Natural":"INSTITUCION PUBLICA","Proyecto":"ASTRO20-0111","etapa":"","Fecha de Transferencia":"2021-08-26","Numero de Cuota":"1","Monto de Transferencia":4841990.0,"Aplicaciones (Rendiciones)":0.0,"Reintegros":0.0,"Saldo":4841990.0,"Presentación Rendición":"8888-08-08","Vigente/Pendiente (según Rendición presentada)":"VIGENTE","Fecha Término de Proyecto":"2022-06-04","Estado según saldo (2 años del giro)":"DEUDA MOROSA"},{"Subdirección":"REDES, ESTRATEGIA Y CONOCIMIENTO (SREC)","Programa":"ASTRONOMIA","Cuenta":"11405270000000","Nombre Cuenta":"APLICACIÓN FONDOS GEMINI","Imputacion":"0","financiamiento":"Adm. Terceros","Beneficiario":"UNIVERSIDAD DE LA SERENA","Público/Privado":"SI","Jurídico/Natural":"INSTITUCION PUBLICA","Proyecto":"ASTRO21-0061","etapa":"","Fecha de Transferencia":"2022-08-24","Numero de Cuota":"1","Monto de Transferencia":27920000.0,"Aplicaciones (Rendiciones)":25847914.0,"Reintegros":0.0,"Saldo":2072086.0,"Presentación Rendición":"8888-08-08","Vigente/Pendiente (según Rendición presentada)":"VIGENTE","Fecha Término de Proyecto":"2024-08-10","Estado según saldo (2 años del giro)":"DEUDA MOROSA"},{"Subdirección":"REDES, ESTRATEGIA Y CONOCIMIENTO (SREC)","Programa":"ASTRONOMIA","Cuenta":"11405270000000","Nombre Cuenta":"APLICACIÓN FONDOS GEMINI","Imputacion":"0","financiamiento":"Adm. Terceros","Beneficiario":"UNIVERSIDAD DE LA SERENA","Público/Privado":"SI","Jurídico/Natural":"INSTITUCION PUBLICA","Proyecto":"ASTRO21-0061","etapa":"","Fecha de Transferencia":"2024-06-26","Numero de Cuota":"C2-2","Monto de Transferencia":27920000.0,"Aplicaciones (Rendiciones)":0.0,"Reintegros":0.0,"Saldo":27920000.0,"Presentación Rendición":"8888-08-08","Vigente/Pendiente (según Rendición presentada)":"VIGENTE","Fecha Término de Proyecto":"2024-08-10","Estado según saldo (2 años del giro)":"DEUDA MOROSA"},{"Subdirección":"REDES, ESTRATEGIA Y CONOCIMIENTO (SREC)","Programa":"ASTRONOMIA","Cuenta":"11405270000000","Nombre Cuenta":"APLICACIÓN FONDOS GEMINI","Imputacion":"0","financiamiento":"Adm. Terceros","Beneficiario":"UNIVERSIDAD DE LA SERENA","Público/Privado":"SI","Jurídico/Natural":"INSTITUCION PUBLICA","Proyecto":"ASTRO21-0067","etapa":"","Fecha de Transferencia":"2022-09-26","Numero de Cuota":"1","Monto de Transferencia":5000000.0,"Aplicaciones (Rendiciones)":0.0,"Reintegros":0.0,"Saldo":5000000.0,"Presentación Rendición":"8888-08-08","Vigente/Pendiente (según Rendición presentada)":"VIGENTE","Fecha Término de Proyecto":"2023-08-12","Estado según saldo (2 años del giro)":"DEUDA MOROSA"},{"Subdirección":"CAPITAL HUMANO (SCH)","Programa":"CHA","Cuenta":"12106010234000","Nombre Cuenta":"Fortalecimiento programa de doctorado","Imputacion":"2401","financiamiento":"ANID","Beneficiario":"UNIVERSIDAD DE LA SERENA","Público/Privado":"SI","Jurídico/Natural":"INSTITUCION PUBLICA","Proyecto":"86220034","etapa":"","Fecha de Transferencia":"2025-05-22","Numero de Cuota":"C3-3","Monto de Transferencia":65000000.0,"Aplicaciones (Rendiciones)":64750000.0,"Reintegros":0.0,"Saldo":250000.0,"Presentación Rendición":"8888-08-08","Vigente/Pendiente (según Rendición presentada)":"VIGENTE","Fecha Término de Proyecto":"2025-12-27","Estado según saldo (2 años del giro)":"DEUDA VENCIDA"},{"Subdirección":"REDES, ESTRATEGIA Y CONOCIMIENTO (SREC)","Programa":"ASTRONOMIA","Cuenta":"12106010746000","Nombre Cuenta":"Deudores Quimal","Imputacion":"2401","financiamiento":"ANID","Beneficiario":"UNIVERSIDAD DE LA SERENA","Público/Privado":"SI","Jurídico/Natural":"INSTITUCION PUBLICA","Proyecto":"QUIMAL220008","etapa":"","Fecha de Transferencia":"2024-12-23","Numero de Cuota":"C3-3","Monto de Transferencia":34120000.0,"Aplicaciones (Rendiciones)":1995000.0,"Reintegros":0.0,"Saldo":32125000.0,"Presentación Rendición":"2027-01-21","Vigente/Pendiente (según Rendición presentada)":"VIGENTE","Fecha Término de Proyecto":"2026-12-21","Estado según saldo (2 años del giro)":"DEUDA VENCIDA"},{"Subdirección":"CAPITAL HUMANO (SCH)","Programa":"CHA","Cuenta":"12106010904000","Nombre Cuenta":"DEUDORES TESIS EN LA INDUSTRIA","Imputacion":"2401","financiamiento":"FIC","Beneficiario":"UNIVERSIDAD DE LA SERENA","Público/Privado":"SI","Jurídico/Natural":"INSTITUCION PUBLICA","Proyecto":"TDP220014","etapa":"","Fecha de Transferencia":"2024-05-27","Numero de Cuota":"C2-2","Monto de Transferencia":17900000.0,"Aplicaciones (Rendiciones)":15661828.0,"Reintegros":0.0,"Saldo":2238172.0,"Presentación Rendición":"8888-08-08","Vigente/Pendiente (según Rendición presentada)":"VIGENTE","Fecha Término de Proyecto":"2025-05-20","Estado según saldo (2 años del giro)":"DEUDA MOROSA"},{"Subdirección":"PROYECTOS DE INVESTIGACIÓN (SPI)","Programa":"FONDECYT","Cuenta":"12106030103000","Nombre Cuenta":"Deudores Regular Institución","Imputacion":"2403","financiamiento":"ANID","Beneficiario":"UNIVERSIDAD DE LA SERENA","Público/Privado":"SI","Jurídico/Natural":"INSTITUCION PUBLICA","Proyecto":"1220134","etapa":"2025 GA","Fecha de Transferencia":"2025-06-18","Numero de Cuota":"C4-4-1","Monto de Transferencia":3540000.0,"Aplicaciones (Rendiciones)":0.0,"Reintegros":0.0,"Saldo":3540000.0,"Presentación Rendición":"8888-08-08","Vigente/Pendiente (según Rendición presentada)":"VIGENTE","Fecha Término de Proyecto":"2026-03-31","Estado según saldo (2 años del giro)":"DEUDA VENCIDA"},{"Subdirección":"PROYECTOS DE INVESTIGACIÓN (SPI)","Programa":"FONDECYT","Cuenta":"12106030103000","Nombre Cuenta":"Deudores Regular Institución","Imputacion":"2403","financiamiento":"ANID","Beneficiario":"UNIVERSIDAD DE LA SERENA","Público/Privado":"SI","Jurídico/Natural":"INSTITUCION PUBLICA","Proyecto":"1220503","etapa":"2025 GA","Fecha de Transferencia":"2025-06-18","Numero de Cuota":"C4-4-1","Monto de Transferencia":8624000.0,"Aplicaciones (Rendiciones)":0.0,"Reintegros":0.0,"Saldo":8624000.0,"Presentación Rendición":"8888-08-08","Vigente/Pendiente (según Rendición presentada)":"VIGENTE","Fecha Término de Proyecto":"2026-03-31","Estado según saldo (2 años del giro)":"DEUDA VENCIDA"},{"Subdirección":"PROYECTOS DE INVESTIGACIÓN (SPI)","Programa":"FONDECYT","Cuenta":"12106030103000","Nombre Cuenta":"Deudores Regular Institución","Imputacion":"2403","financiamiento":"ANID","Beneficiario":"UNIVERSIDAD DE LA SERENA","Público/Privado":"SI","Jurídico/Natural":"INSTITUCION PUBLICA","Proyecto":"1221827","etapa":"2025 GA","Fecha de Transferencia":"2025-11-28","Numero de Cuota":"C4-4-1","Monto de Transferencia":4564000.0,"Aplicaciones (Rendiciones)":0.0,"Reintegros":0.0,"Saldo":4564000.0,"Presentación Rendición":"8888-08-08","Vigente/Pendiente (según Rendición presentada)":"VIGENTE","Fecha Término de Proyecto":"2026-07-31","Estado según saldo (2 años del giro)":"DEUDA SIN RETRASO"},{"Subdirección":"PROYECTOS DE INVESTIGACIÓN (SPI)","Programa":"FONDECYT","Cuenta":"12106030103000","Nombre Cuenta":"Deudores Regular Institución","Imputacion":"2403","financiamiento":"ANID","Beneficiario":"UNIVERSIDAD DE LA SERENA","Público/Privado":"SI","Jurídico/Natural":"INSTITUCION PUBLICA","Proyecto":"1221928","etapa":"2025 GA","Fecha de Transferencia":"2025-10-27","Numero de Cuota":"C4-4-1","Monto de Transferencia":1110000.0,"Aplicaciones (Rendiciones)":0.0,"Reintegros":0.0,"Saldo":1110000.0,"Presentación Rendición":"8888-08-08","Vigente/Pendiente (según Rendición presentada)":"VIGENTE","Fecha Término de Proyecto":"2026-03-31","Estado según saldo (2 años del giro)":"DEUDA SIN RETRASO"},{"Subdirección":"PROYECTOS DE INVESTIGACIÓN (SPI)","Programa":"FONDECYT","Cuenta":"12106030103000","Nombre Cuenta":"Deudores Regular Institución","Imputacion":"2403","financiamiento":"ANID","Beneficiario":"UNIVERSIDAD DE LA SERENA","Público/Privado":"SI","Jurídico/Natural":"INSTITUCION PUBLICA","Proyecto":"1230160","etapa":"2025 GA","Fecha de Transferencia":"2025-06-18","Numero de Cuota":"C3-4-1","Monto de Transferencia":2000000.0,"Aplicaciones (Rendiciones)":0.0,"Reintegros":0.0,"Saldo":2000000.0,"Presentación Rendición":"2026-07-22","Vigente/Pendiente (según Rendición presentada)":"VIGENTE","Fecha Término de Proyecto":"2027-03-31","Estado según saldo (2 años del giro)":"DEUDA VENCIDA"},{"Subdirección":"PROYECTOS DE INVESTIGACIÓN (SPI)","Programa":"FONDECYT","Cuenta":"12106030103000","Nombre Cuenta":"Deudores Regular Institución","Imputacion":"2403","financiamiento":"ANID","Beneficiario":"UNIVERSIDAD DE LA SERENA","Público/Privado":"SI","Jurídico/Natural":"INSTITUCION PUBLICA","Proyecto":"1230179","etapa":"2025 GA","Fecha de Transferencia":"2025-06-18","Numero de Cuota":"C3-3-1","Monto de Transferencia":4140000.0,"Aplicaciones (Rendiciones)":0.0,"Reintegros":0.0,"Saldo":4140000.0,"Presentación Rendición":"8888-08-08","Vigente/Pendiente (según Rendición presentada)":"VIGENTE","Fecha Término de Proyecto":"2026-03-31","Estado según saldo (2 años del giro)":"DEUDA VENCIDA"},{"Subdirección":"PROYECTOS DE INVESTIGACIÓN (SPI)","Programa":"FONDECYT","Cuenta":"12106030103000","Nombre Cuenta":"Deudores Regular Institución","Imputacion":"2403","financiamiento":"ANID","Beneficiario":"UNIVERSIDAD DE LA SERENA","Público/Privado":"SI","Jurídico/Natural":"INSTITUCION PUBLICA","Proyecto":"1230483","etapa":"2025 GA","Fecha de Transferencia":"2025-06-18","Numero de Cuota":"C3-4-1","Monto de Transferencia":5132000.0,"Aplicaciones (Rendiciones)":0.0,"Reintegros":0.0,"Saldo":5132000.0,"Presentación Rendición":"2026-07-22","Vigente/Pendiente (según Rendición presentada)":"VIGENTE","Fecha Término de Proyecto":"2027-03-31","Estado según saldo (2 años del giro)":"DEUDA VENCIDA"},{"Subdirección":"PROYECTOS DE INVESTIGACIÓN (SPI)","Programa":"FONDECYT","Cuenta":"12106030103000","Nombre Cuenta":"Deudores Regular Institución","Imputacion":"2403","financiamiento":"ANID","Beneficiario":"UNIVERSIDAD DE LA SERENA","Público/Privado":"SI","Jurídico/Natural":"INSTITUCION PUBLICA","Proyecto":"1230857","etapa":"2025 GA","Fecha de Transferencia":"2025-06-18","Numero de Cuota":"C3-4-1","Monto de Transferencia":9720000.0,"Aplicaciones (Rendiciones)":0.0,"Reintegros":0.0,"Saldo":9720000.0,"Presentación Rendición":"2026-07-22","Vigente/Pendiente (según Rendición presentada)":"VIGENTE","Fecha Término de Proyecto":"2027-03-31","Estado según saldo (2 años del giro)":"DEUDA VENCIDA"},{"Subdirección":"PROYECTOS DE INVESTIGACIÓN (SPI)","Programa":"FONDECYT","Cuenta":"12106030103000","Nombre Cuenta":"Deudores Regular Institución","Imputacion":"2403","financiamiento":"ANID","Beneficiario":"UNIVERSIDAD DE LA SERENA","Público/Privado":"SI","Jurídico/Natural":"INSTITUCION PUBLICA","Proyecto":"1230870","etapa":"2025 GA","Fecha de Transferencia":"2025-06-18","Numero de Cuota":"C3-3-1","Monto de Transferencia":80000.0,"Aplicaciones (Rendiciones)":0.0,"Reintegros":0.0,"Saldo":80000.0,"Presentación Rendición":"8888-08-08","Vigente/Pendiente (según Rendición presentada)":"VIGENTE","Fecha Término de Proyecto":"2026-03-31","Estado según saldo (2 años del giro)":"DEUDA VENCIDA"},{"Subdirección":"PROYECTOS DE INVESTIGACIÓN (SPI)","Programa":"FONDECYT","Cuenta":"12106030103000","Nombre Cuenta":"Deudores Regular Institución","Imputacion":"2403","financiamiento":"ANID","Beneficiario":"UNIVERSIDAD DE LA SERENA","Público/Privado":"SI","Jurídico/Natural":"INSTITUCION PUBLICA","Proyecto":"1231248","etapa":"2025 GA","Fecha de Transferencia":"2025-06-18","Numero de Cuota":"C3-4-1","Monto de Transferencia":2300000.0,"Aplicaciones (Rendiciones)":0.0,"Reintegros":0.0,"Saldo":2300000.0,"Presentación Rendición":"2026-07-22","Vigente/Pendiente (según Rendición presentada)":"VIGENTE","Fecha Término de Proyecto":"2027-03-31","Estado según saldo (2 años del giro)":"DEUDA VENCIDA"},{"Subdirección":"PROYECTOS DE INVESTIGACIÓN (SPI)","Programa":"FONDECYT","Cuenta":"12106030103000","Nombre Cuenta":"Deudores Regular Institución","Imputacion":"2403","financiamiento":"ANID","Beneficiario":"UNIVERSIDAD DE LA SERENA","Público/Privado":"SI","Jurídico/Natural":"INSTITUCION PUBLICA","Proyecto":"1231667","etapa":"2025 GA","Fecha de Transferencia":"2025-10-27","Numero de Cuota":"C3-3-1","Monto de Transferencia":2734000.0,"Aplicaciones (Rendiciones)":0.0,"Reintegros":0.0,"Saldo":2734000.0,"Presentación Rendición":"8888-08-08","Vigente/Pendiente (según Rendición presentada)":"VIGENTE","Fecha Término de Proyecto":"2026-07-31","Estado según saldo (2 años del giro)":"DEUDA SIN RETRASO"},{"Subdirección":"PROYECTOS DE INVESTIGACIÓN (SPI)","Programa":"FONDECYT","Cuenta":"12106030103000","Nombre Cuenta":"Deudores Regular Institución","Imputacion":"2403","financiamiento":"ANID","Beneficiario":"UNIVERSIDAD DE LA SERENA","Público/Privado":"SI","Jurídico/Natural":"INSTITUCION PUBLICA","Proyecto":"1231891","etapa":"2025 GA","Fecha de Transferencia":"2025-06-18","Numero de Cuota":"C3-3-1","Monto de Transferencia":1309000.0,"Aplicaciones (Rendiciones)":0.0,"Reintegros":0.0,"Saldo":1309000.0,"Presentación Rendición":"8888-08-08","Vigente/Pendiente (según Rendición presentada)":"VIGENTE","Fecha Término de Proyecto":"2026-03-31","Estado según saldo (2 años del giro)":"DEUDA VENCIDA"},{"Subdirección":"PROYECTOS DE INVESTIGACIÓN (SPI)","Programa":"FONDECYT","Cuenta":"12106030103000","Nombre Cuenta":"Deudores Regular Institución","Imputacion":"2403","financiamiento":"ANID","Beneficiario":"UNIVERSIDAD DE LA SERENA","Público/Privado":"SI","Jurídico/Natural":"INSTITUCION PUBLICA","Proyecto":"1240404","etapa":"2025 GA","Fecha de Transferencia":"2025-06-18","Numero de Cuota":"C2-3-1","Monto de Transferencia":9270000.0,"Aplicaciones (Rendiciones)":0.0,"Reintegros":0.0,"Saldo":9270000.0,"Presentación Rendición":"2026-07-22","Vigente/Pendiente (según Rendición presentada)":"VIGENTE","Fecha Término de Proyecto":"2027-03-31","Estado según saldo (2 años del giro)":"DEUDA VENCIDA"},{"Subdirección":"PROYECTOS DE INVESTIGACIÓN (SPI)","Programa":"FONDECYT","Cuenta":"12106030103000","Nombre Cuenta":"Deudores Regular Institución","Imputacion":"2403","financiamiento":"ANID","Beneficiario":"UNIVERSIDAD DE LA SERENA","Público/Privado":"SI","Jurídico/Natural":"INSTITUCION PUBLICA","Proyecto":"1240404","etapa":"2025 GA","Fecha de Transferencia":"2025-12-31","Numero de Cuota":"C2-3-2","Monto de Transferencia":389000.0,"Aplicaciones (Rendiciones)":0.0,"Reintegros":0.0,"Saldo":389000.0,"Presentación Rendición":"2027-01-22","Vigente/Pendiente (según Rendición presentada)":"VIGENTE","Fecha Término de Proyecto":"2027-03-31","Estado según saldo (2 años del giro)":"DEUDA SIN RETRASO"},{"Subdirección":"PROYECTOS DE INVESTIGACIÓN (SPI)","Programa":"FONDECYT","Cuenta":"12106030103000","Nombre Cuenta":"Deudores Regular Institución","Imputacion":"2403","financiamiento":"ANID","Beneficiario":"UNIVERSIDAD DE LA SERENA","Público/Privado":"SI","Jurídico/Natural":"INSTITUCION PUBLICA","Proyecto":"1241565","etapa":"2025 GA","Fecha de Transferencia":"2025-06-18","Numero de Cuota":"C2-4-1","Monto de Transferencia":9765000.0,"Aplicaciones (Rendiciones)":0.0,"Reintegros":0.0,"Saldo":9765000.0,"Presentación Rendición":"2026-07-22","Vigente/Pendiente (según Rendición presentada)":"VIGENTE","Fecha Término de Proyecto":"2028-03-31","Estado según saldo (2 años del giro)":"DEUDA VENCIDA"},{"Subdirección":"PROYECTOS DE INVESTIGACIÓN (SPI)","Programa":"FONDECYT","Cuenta":"12106030103000","Nombre Cuenta":"Deudores Regular Institución","Imputacion":"2403","financiamiento":"ANID","Beneficiario":"UNIVERSIDAD DE LA SERENA","Público/Privado":"SI","Jurídico/Natural":"INSTITUCION PUBLICA","Proyecto":"1241565","etapa":"2025 GA","Fecha de Transferencia":"2025-12-31","Numero de Cuota":"C2-4-2","Monto de Transferencia":410000.0,"Aplicaciones (Rendiciones)":0.0,"Reintegros":0.0,"Saldo":410000.0,"Presentación Rendición":"2027-01-22","Vigente/Pendiente (según Rendición presentada)":"VIGENTE","Fecha Término de Proyecto":"2028-03-31","Estado según saldo (2 años del giro)":"DEUDA SIN RETRASO"},{"Subdirección":"PROYECTOS DE INVESTIGACIÓN (SPI)","Programa":"FONDECYT","Cuenta":"12106030103000","Nombre Cuenta":"Deudores Regular Institución","Imputacion":"2403","financiamiento":"ANID","Beneficiario":"UNIVERSIDAD DE LA SERENA","Público/Privado":"SI","Jurídico/Natural":"INSTITUCION PUBLICA","Proyecto":"1241685","etapa":"2025 GA","Fecha de Transferencia":"2025-06-18","Numero de Cuota":"C2-4-1","Monto de Transferencia":7954000.0,"Aplicaciones (Rendiciones)":0.0,"Reintegros":0.0,"Saldo":7954000.0,"Presentación Rendición":"2026-07-22","Vigente/Pendiente (según Rendición presentada)":"VIGENTE","Fecha Término de Proyecto":"2028-03-31","Estado según saldo (2 años del giro)":"DEUDA VENCIDA"},{"Subdirección":"PROYECTOS DE INVESTIGACIÓN (SPI)","Programa":"FONDECYT","Cuenta":"12106030103000","Nombre Cuenta":"Deudores Regular Institución","Imputacion":"2403","financiamiento":"ANID","Beneficiario":"UNIVERSIDAD DE LA SERENA","Público/Privado":"SI","Jurídico/Natural":"INSTITUCION PUBLICA","Proyecto":"1241685","etapa":"2025 GA","Fecha de Transferencia":"2025-12-31","Numero de Cuota":"C2-4-2","Monto de Transferencia":334000.0,"Aplicaciones (Rendiciones)":0.0,"Reintegros":0.0,"Saldo":334000.0,"Presentación Rendición":"2027-01-22","Vigente/Pendiente (según Rendición presentada)":"VIGENTE","Fecha Término de Proyecto":"2028-03-31","Estado según saldo (2 años del giro)":"DEUDA SIN RETRASO"},{"Subdirección":"PROYECTOS DE INVESTIGACIÓN (SPI)","Programa":"FONDECYT","Cuenta":"12106030103000","Nombre Cuenta":"Deudores Regular Institución","Imputacion":"2403","financiamiento":"ANID","Beneficiario":"UNIVERSIDAD DE LA SERENA","Público/Privado":"SI","Jurídico/Natural":"INSTITUCION PUBLICA","Proyecto":"1241803","etapa":"2025 GA","Fecha de Transferencia":"2025-12-31","Numero de Cuota":"C2-4-2","Monto de Transferencia":394000.0,"Aplicaciones (Rendiciones)":0.0,"Reintegros":0.0,"Saldo":394000.0,"Presentación Rendición":"2027-01-22","Vigente/Pendiente (según Rendición presentada)":"VIGENTE","Fecha Término de Proyecto":"2028-03-31","Estado según saldo (2 años del giro)":"DEUDA SIN RETRASO"},{"Subdirección":"PROYECTOS DE INVESTIGACIÓN (SPI)","Programa":"FONDECYT","Cuenta":"12106030103000","Nombre Cuenta":"Deudores Regular Institución","Imputacion":"2403","financiamiento":"ANID","Beneficiario":"UNIVERSIDAD DE LA SERENA","Público/Privado":"SI","Jurídico/Natural":"INSTITUCION PUBLICA","Proyecto":"1241803","etapa":"2025 GA","Fecha de Transferencia":"2025-06-18","Numero de Cuota":"C2-4-1","Monto de Transferencia":9390000.0,"Aplicaciones (Rendiciones)":0.0,"Reintegros":0.0,"Saldo":9390000.0,"Presentación Rendición":"2026-07-22","Vigente/Pendiente (según Rendición presentada)":"VIGENTE","Fecha Término de Proyecto":"2028-03-31","Estado según saldo (2 años del giro)":"DEUDA VENCIDA"},{"Subdirección":"PROYECTOS DE INVESTIGACIÓN (SPI)","Programa":"FONDECYT","Cuenta":"12106030103000","Nombre Cuenta":"Deudores Regular Institución","Imputacion":"2403","financiamiento":"ANID","Beneficiario":"UNIVERSIDAD DE LA SERENA","Público/Privado":"SI","Jurídico/Natural":"INSTITUCION PUBLICA","Proyecto":"1241847","etapa":"2025 GA","Fecha de Transferencia":"2025-06-18","Numero de Cuota":"C2-4-1","Monto de Transferencia":9098000.0,"Aplicaciones (Rendiciones)":0.0,"Reintegros":0.0,"Saldo":9098000.0,"Presentación Rendición":"2026-07-22","Vigente/Pendiente (según Rendición presentada)":"VIGENTE","Fecha Término de Proyecto":"2028-03-31","Estado según saldo (2 años del giro)":"DEUDA VENCIDA"},{"Subdirección":"PROYECTOS DE INVESTIGACIÓN (SPI)","Programa":"FONDECYT","Cuenta":"12106030103000","Nombre Cuenta":"Deudores Regular Institución","Imputacion":"2403","financiamiento":"ANID","Beneficiario":"UNIVERSIDAD DE LA SERENA","Público/Privado":"SI","Jurídico/Natural":"INSTITUCION PUBLICA","Proyecto":"1241847","etapa":"2025 GA","Fecha de Transferencia":"2025-12-31","Numero de Cuota":"C2-4-2","Monto de Transferencia":382000.0,"Aplicaciones (Rendiciones)":0.0,"Reintegros":0.0,"Saldo":382000.0,"Presentación Rendición":"2027-01-22","Vigente/Pendiente (según Rendición presentada)":"VIGENTE","Fecha Término de Proyecto":"2028-03-31","Estado según saldo (2 años del giro)":"DEUDA SIN RETRASO"},{"Subdirección":"PROYECTOS DE INVESTIGACIÓN (SPI)","Programa":"FONDECYT","Cuenta":"12106030103000","Nombre Cuenta":"Deudores Regular Institución","Imputacion":"2403","financiamiento":"ANID","Beneficiario":"UNIVERSIDAD DE LA SERENA","Público/Privado":"SI","Jurídico/Natural":"INSTITUCION PUBLICA","Proyecto":"1250233","etapa":"2025 GA","Fecha de Transferencia":"2025-09-15","Numero de Cuota":"C1-3-1","Monto de Transferencia":1680000.0,"Aplicaciones (Rendiciones)":0.0,"Reintegros":0.0,"Saldo":1680000.0,"Presentación Rendición":"2026-10-22","Vigente/Pendiente (según Rendición presentada)":"VIGENTE","Fecha Término de Proyecto":"2028-03-31","Estado según saldo (2 años del giro)":"DEUDA SIN RETRASO"},{"Subdirección":"PROYECTOS DE INVESTIGACIÓN (SPI)","Programa":"FONDECYT","Cuenta":"12106030103000","Nombre Cuenta":"Deudores Regular Institución","Imputacion":"2403","financiamiento":"ANID","Beneficiario":"UNIVERSIDAD DE LA SERENA","Público/Privado":"SI","Jurídico/Natural":"INSTITUCION PUBLICA","Proyecto":"1250343","etapa":"2025 GA","Fecha de Transferencia":"2025-09-15","Numero de Cuota":"C1-4-1","Monto de Transferencia":5750000.0,"Aplicaciones (Rendiciones)":0.0,"Reintegros":0.0,"Saldo":5750000.0,"Presentación Rendición":"2026-10-22","Vigente/Pendiente (según Rendición presentada)":"VIGENTE","Fecha Término de Proyecto":"2029-03-31","Estado según saldo (2 años del giro)":"DEUDA SIN RETRASO"},{"Subdirección":"PROYECTOS DE INVESTIGACIÓN (SPI)","Programa":"FONDECYT","Cuenta":"12106030103000","Nombre Cuenta":"Deudores Regular Institución","Imputacion":"2403","financiamiento":"ANID","Beneficiario":"UNIVERSIDAD DE LA SERENA","Público/Privado":"SI","Jurídico/Natural":"INSTITUCION PUBLICA","Proyecto":"1250475","etapa":"2025 GA","Fecha de Transferencia":"2025-09-15","Numero de Cuota":"C1-3-1","Monto de Transferencia":1820000.0,"Aplicaciones (Rendiciones)":0.0,"Reintegros":0.0,"Saldo":1820000.0,"Presentación Rendición":"2026-10-22","Vigente/Pendiente (según Rendición presentada)":"VIGENTE","Fecha Término de Proyecto":"2028-03-31","Estado según saldo (2 años del giro)":"DEUDA SIN RETRASO"},{"Subdirección":"PROYECTOS DE INVESTIGACIÓN (SPI)","Programa":"FONDECYT","Cuenta":"12106030103000","Nombre Cuenta":"Deudores Regular Institución","Imputacion":"2403","financiamiento":"ANID","Beneficiario":"UNIVERSIDAD DE LA SERENA","Público/Privado":"SI","Jurídico/Natural":"INSTITUCION PUBLICA","Proyecto":"1250559","etapa":"2025 GA","Fecha de Transferencia":"2025-07-29","Numero de Cuota":"C1-4-1","Monto de Transferencia":1150000.0,"Aplicaciones (Rendiciones)":0.0,"Reintegros":0.0,"Saldo":1150000.0,"Presentación Rendición":"2026-08-24","Vigente/Pendiente (según Rendición presentada)":"VIGENTE","Fecha Término de Proyecto":"2029-03-31","Estado según saldo (2 años del giro)":"DEUDA SIN RETRASO"},{"Subdirección":"PROYECTOS DE INVESTIGACIÓN (SPI)","Programa":"FONDECYT","Cuenta":"12106030103000","Nombre Cuenta":"Deudores Regular Institución","Imputacion":"2403","financiamiento":"ANID","Beneficiario":"UNIVERSIDAD DE LA SERENA","Público/Privado":"SI","Jurídico/Natural":"INSTITUCION PUBLICA","Proyecto":"1251493","etapa":"2025 GA","Fecha de Transferencia":"2025-09-15","Numero de Cuota":"C1-4-1","Monto de Transferencia":4730000.0,"Aplicaciones (Rendiciones)":0.0,"Reintegros":0.0,"Saldo":4730000.0,"Presentación Rendición":"2026-10-22","Vigente/Pendiente (según Rendición presentada)":"VIGENTE","Fecha Término de Proyecto":"2029-03-31","Estado según saldo (2 años del giro)":"DEUDA SIN RETRASO"},{"Subdirección":"PROYECTOS DE INVESTIGACIÓN (SPI)","Programa":"FONDECYT","Cuenta":"12106030103000","Nombre Cuenta":"Deudores Regular Institución","Imputacion":"2403","financiamiento":"ANID","Beneficiario":"UNIVERSIDAD DE LA SERENA","Público/Privado":"SI","Jurídico/Natural":"INSTITUCION PUBLICA","Proyecto":"1251882","etapa":"2025 GA","Fecha de Transferencia":"2025-09-15","Numero de Cuota":"C1-4-1","Monto de Transferencia":4020000.0,"Aplicaciones (Rendiciones)":0.0,"Reintegros":0.0,"Saldo":4020000.0,"Presentación Rendición":"2026-10-22","Vigente/Pendiente (según Rendición presentada)":"VIGENTE","Fecha Término de Proyecto":"2029-03-31","Estado según saldo (2 años del giro)":"DEUDA SIN RETRASO"},{"Subdirección":"PROYECTOS DE INVESTIGACIÓN (SPI)","Programa":"FONDECYT","Cuenta":"12106030103000","Nombre Cuenta":"Deudores Regular Institución","Imputacion":"2403","financiamiento":"ANID","Beneficiario":"UNIVERSIDAD DE LA SERENA","Público/Privado":"SI","Jurídico/Natural":"INSTITUCION PUBLICA","Proyecto":"1251961","etapa":"2025 GA","Fecha de Transferencia":"2025-09-15","Numero de Cuota":"C1-4-1","Monto de Transferencia":7963000.0,"Aplicaciones (Rendiciones)":0.0,"Reintegros":0.0,"Saldo":7963000.0,"Presentación Rendición":"2026-10-22","Vigente/Pendiente (según Rendición presentada)":"VIGENTE","Fecha Término de Proyecto":"2029-03-31","Estado según saldo (2 años del giro)":"DEUDA SIN RETRASO"},{"Subdirección":"PROYECTOS DE INVESTIGACIÓN (SPI)","Programa":"FONDECYT","Cuenta":"12106030105000","Nombre Cuenta":"Deudores Regular Iniciación Bienes de Capital ","Imputacion":"2403","financiamiento":"ANID","Beneficiario":"UNIVERSIDAD DE LA SERENA","Público/Privado":"SI","Jurídico/Natural":"INSTITUCION PUBLICA","Proyecto":"11230866","etapa":"2025 GA","Fecha de Transferencia":"2025-06-18","Numero de Cuota":"C3-3-1","Monto de Transferencia":4186000.0,"Aplicaciones (Rendiciones)":0.0,"Reintegros":0.0,"Saldo":4186000.0,"Presentación Rendición":"8888-08-08","Vigente/Pendiente (según Rendición presentada)":"VIGENTE","Fecha Término de Proyecto":"2026-03-14","Estado según saldo (2 años del giro)":"DEUDA VENCIDA"},{"Subdirección":"PROYECTOS DE INVESTIGACIÓN (SPI)","Programa":"FONDECYT","Cuenta":"12106030105000","Nombre Cuenta":"Deudores Regular Iniciación Bienes de Capital ","Imputacion":"2403","financiamiento":"ANID","Beneficiario":"UNIVERSIDAD DE LA SERENA","Público/Privado":"SI","Jurídico/Natural":"INSTITUCION PUBLICA","Proyecto":"11241154","etapa":"2025 GA","Fecha de Transferencia":"2025-06-18","Numero de Cuota":"C2-3-1","Monto de Transferencia":4620000.0,"Aplicaciones (Rendiciones)":0.0,"Reintegros":0.0,"Saldo":4620000.0,"Presentación Rendición":"2026-07-22","Vigente/Pendiente (según Rendición presentada)":"VIGENTE","Fecha Término de Proyecto":"2027-03-14","Estado según saldo (2 años del giro)":"DEUDA VENCIDA"},{"Subdirección":"PROYECTOS DE INVESTIGACIÓN (SPI)","Programa":"FONDECYT","Cuenta":"12106030105000","Nombre Cuenta":"Deudores Regular Iniciación Bienes de Capital ","Imputacion":"2403","financiamiento":"ANID","Beneficiario":"UNIVERSIDAD DE LA SERENA","Público/Privado":"SI","Jurídico/Natural":"INSTITUCION PUBLICA","Proyecto":"11241154","etapa":"2025 GA","Fecha de Transferencia":"2025-12-31","Numero de Cuota":"C2-3-2","Monto de Transferencia":194000.0,"Aplicaciones (Rendiciones)":0.0,"Reintegros":0.0,"Saldo":194000.0,"Presentación Rendición":"2027-01-22","Vigente/Pendiente (según Rendición presentada)":"VIGENTE","Fecha Término de Proyecto":"2027-03-14","Estado según saldo (2 años del giro)":"DEUDA SIN RETRASO"},{"Subdirección":"PROYECTOS DE INVESTIGACIÓN (SPI)","Programa":"FONDECYT","Cuenta":"12106030105000","Nombre Cuenta":"Deudores Regular Iniciación Bienes de Capital ","Imputacion":"2403","financiamiento":"ANID","Beneficiario":"UNIVERSIDAD DE LA SERENA","Público/Privado":"SI","Jurídico/Natural":"INSTITUCION PUBLICA","Proyecto":"11241164","etapa":"2025 GA","Fecha de Transferencia":"2025-12-31","Numero de Cuota":"C2-3-2","Monto de Transferencia":165000.0,"Aplicaciones (Rendiciones)":0.0,"Reintegros":0.0,"Saldo":165000.0,"Presentación Rendición":"2027-01-22","Vigente/Pendiente (según Rendición presentada)":"VIGENTE","Fecha Término de Proyecto":"2027-03-14","Estado según saldo (2 años del giro)":"DEUDA SIN RETRASO"},{"Subdirección":"PROYECTOS DE INVESTIGACIÓN (SPI)","Programa":"FONDECYT","Cuenta":"12106030105000","Nombre Cuenta":"Deudores Regular Iniciación Bienes de Capital ","Imputacion":"2403","financiamiento":"ANID","Beneficiario":"UNIVERSIDAD DE LA SERENA","Público/Privado":"SI","Jurídico/Natural":"INSTITUCION PUBLICA","Proyecto":"11241164","etapa":"2025 GA","Fecha de Transferencia":"2025-06-18","Numero de Cuota":"C2-3-1","Monto de Transferencia":3940000.0,"Aplicaciones (Rendiciones)":0.0,"Reintegros":0.0,"Saldo":3940000.0,"Presentación Rendición":"2026-07-22","Vigente/Pendiente (según Rendición presentada)":"VIGENTE","Fecha Término de Proyecto":"2027-03-14","Estado según saldo (2 años del giro)":"DEUDA VENCIDA"},{"Subdirección":"PROYECTOS DE INVESTIGACIÓN (SPI)","Programa":"FONDECYT","Cuenta":"12106030105000","Nombre Cuenta":"Deudores Regular Iniciación Bienes de Capital ","Imputacion":"2403","financiamiento":"ANID","Beneficiario":"UNIVERSIDAD DE LA SERENA","Público/Privado":"SI","Jurídico/Natural":"INSTITUCION PUBLICA","Proyecto":"11250233","etapa":"2025 GA","Fecha de Transferencia":"2025-07-29","Numero de Cuota":"C1-3-1","Monto de Transferencia":4800000.0,"Aplicaciones (Rendiciones)":0.0,"Reintegros":0.0,"Saldo":4800000.0,"Presentación Rendición":"2026-08-24","Vigente/Pendiente (según Rendición presentada)":"VIGENTE","Fecha Término de Proyecto":"2028-03-31","Estado según saldo (2 años del giro)":"DEUDA SIN RETRASO"},{"Subdirección":"PROYECTOS DE INVESTIGACIÓN (SPI)","Programa":"FONDECYT","Cuenta":"12106030105000","Nombre Cuenta":"Deudores Regular Iniciación Bienes de Capital ","Imputacion":"2403","financiamiento":"ANID","Beneficiario":"UNIVERSIDAD DE LA SERENA","Público/Privado":"SI","Jurídico/Natural":"INSTITUCION PUBLICA","Proyecto":"11251749","etapa":"2025 GA","Fecha de Transferencia":"2025-09-12","Numero de Cuota":"C1-3-1","Monto de Transferencia":4800000.0,"Aplicaciones (Rendiciones)":0.0,"Reintegros":0.0,"Saldo":4800000.0,"Presentación Rendición":"2026-10-22","Vigente/Pendiente (según Rendición presentada)":"VIGENTE","Fecha Término de Proyecto":"2028-03-31","Estado según saldo (2 años del giro)":"DEUDA SIN RETRASO"},{"Subdirección":"PROYECTOS DE INVESTIGACIÓN (SPI)","Programa":"FONDECYT","Cuenta":"12106030105000","Nombre Cuenta":"Deudores Regular Iniciación Bienes de Capital ","Imputacion":"2403","financiamiento":"ANID","Beneficiario":"UNIVERSIDAD DE LA SERENA","Público/Privado":"SI","Jurídico/Natural":"INSTITUCION PUBLICA","Proyecto":"11251912","etapa":"2025 GA","Fecha de Transferencia":"2025-07-29","Numero de Cuota":"C1-3-1","Monto de Transferencia":4320000.0,"Aplicaciones (Rendiciones)":0.0,"Reintegros":0.0,"Saldo":4320000.0,"Presentación Rendición":"2026-08-24","Vigente/Pendiente (según Rendición presentada)":"VIGENTE","Fecha Término de Proyecto":"2028-03-31","Estado según saldo (2 años del giro)":"DEUDA SIN RETRASO"},{"Subdirección":"PROYECTOS DE INVESTIGACIÓN (SPI)","Programa":"FONDECYT","Cuenta":"12106030105000","Nombre Cuenta":"Deudores Regular Iniciación Bienes de Capital ","Imputacion":"2403","financiamiento":"ANID","Beneficiario":"UNIVERSIDAD DE LA SERENA","Público/Privado":"SI","Jurídico/Natural":"INSTITUCION PUBLICA","Proyecto":"11251931","etapa":"2025 GA","Fecha de Transferencia":"2025-07-29","Numero de Cuota":"C1-3-1","Monto de Transferencia":4794000.0,"Aplicaciones (Rendiciones)":0.0,"Reintegros":0.0,"Saldo":4794000.0,"Presentación Rendición":"2026-08-24","Vigente/Pendiente (según Rendición presentada)":"VIGENTE","Fecha Término de Proyecto":"2028-03-31","Estado según saldo (2 años del giro)":"DEUDA SIN RETRASO"},{"Subdirección":"PROYECTOS DE INVESTIGACIÓN (SPI)","Programa":"FONDECYT","Cuenta":"12106030107000","Nombre Cuenta":"DEUDORES EXPLORACIÓN","Imputacion":"2403","financiamiento":"ANID","Beneficiario":"UNIVERSIDAD DE LA SERENA","Público/Privado":"SI","Jurídico/Natural":"INSTITUCION PUBLICA","Proyecto":"13250002","etapa":"2025 GA","Fecha de Transferencia":"2025-12-31","Numero de Cuota":"C1-4-1","Monto de Transferencia":16000000.0,"Aplicaciones (Rendiciones)":0.0,"Reintegros":0.0,"Saldo":16000000.0,"Presentación Rendición":"2027-01-22","Vigente/Pendiente (según Rendición presentada)":"VIGENTE","Fecha Término de Proyecto":"2029-07-31","Estado según saldo (2 años del giro)":"DEUDA SIN RETRASO"},{"Subdirección":"INVESTIGACIÓN APLICADA (SIA)","Programa":"FONDEF","Cuenta":"12106030201000","Nombre Cuenta":"DEUDORES FONDEF ID","Imputacion":"2403","financiamiento":"ANID","Beneficiario":"UNIVERSIDAD DE LA SERENA","Público/Privado":"SI","Jurídico/Natural":"INSTITUCION PUBLICA","Proyecto":"ID25I10158","etapa":"","Fecha de Transferencia":"2025-09-09","Numero de Cuota":"C1-2","Monto de Transferencia":118471753.0,"Aplicaciones (Rendiciones)":30684580.0,"Reintegros":0.0,"Saldo":87787173.0,"Presentación Rendición":"2026-10-22","Vigente/Pendiente (según Rendición presentada)":"VIGENTE","Fecha Término de Proyecto":"2027-07-01","Estado según saldo (2 años del giro)":"DEUDA SIN RETRASO"},{"Subdirección":"INVESTIGACIÓN APLICADA (SIA)","Programa":"FONDEF","Cuenta":"12106030201000","Nombre Cuenta":"DEUDORES FONDEF ID","Imputacion":"2403","financiamiento":"ANID","Beneficiario":"UNIVERSIDAD DE LA SERENA","Público/Privado":"SI","Jurídico/Natural":"INSTITUCION PUBLICA","Proyecto":"ID25I10329","etapa":"","Fecha de Transferencia":"2025-10-10","Numero de Cuota":"C1-2","Monto de Transferencia":36224609.0,"Aplicaciones (Rendiciones)":0.0,"Reintegros":0.0,"Saldo":36224609.0,"Presentación Rendición":"2026-10-22","Vigente/Pendiente (según Rendición presentada)":"VIGENTE","Fecha Término de Proyecto":"2027-09-30","Estado según saldo (2 años del giro)":"DEUDA SIN RETRASO"},{"Subdirección":"INVESTIGACIÓN APLICADA (SIA)","Programa":"FONDEF","Cuenta":"12106030201000","Nombre Cuenta":"DEUDORES FONDEF ID","Imputacion":"2403","financiamiento":"ANID","Beneficiario":"UNIVERSIDAD DE LA SERENA","Público/Privado":"SI","Jurídico/Natural":"INSTITUCION PUBLICA","Proyecto":"ID25I10628","etapa":"","Fecha de Transferencia":"2025-09-09","Numero de Cuota":"C1-2","Monto de Transferencia":118631700.0,"Aplicaciones (Rendiciones)":0.0,"Reintegros":0.0,"Saldo":118631700.0,"Presentación Rendición":"2026-10-22","Vigente/Pendiente (según Rendición presentada)":"VIGENTE","Fecha Término de Proyecto":"2027-07-01","Estado según saldo (2 años del giro)":"DEUDA SIN RETRASO"},{"Subdirección":"CENTROS E INVESTIGACIÓN ASOCIATIVA (SCIA)","Programa":"PIA","Cuenta":"12106030801000","Nombre Cuenta":"Anillos de Investigación en Ciencia y Tecnología","Imputacion":"2403","financiamiento":"ANID","Beneficiario":"UNIVERSIDAD DE LA SERENA","Público/Privado":"SI","Jurídico/Natural":"INSTITUCION PUBLICA","Proyecto":"ATE220054","etapa":"","Fecha de Transferencia":"2024-11-25","Numero de Cuota":"C3-3","Monto de Transferencia":150000000.0,"Aplicaciones (Rendiciones)":142257693.0,"Reintegros":0.0,"Saldo":7742307.0,"Presentación Rendición":"8888-08-08","Vigente/Pendiente (según Rendición presentada)":"VIGENTE","Fecha Término de Proyecto":"2026-05-17","Estado según saldo (2 años del giro)":"DEUDA VENCIDA"},{"Subdirección":"REDES, ESTRATEGIA Y CONOCIMIENTO (SREC)","Programa":"PCI","Cuenta":"12106031400100","Nombre Cuenta":"INES ESTATALES","Imputacion":"2403","financiamiento":"ANID","Beneficiario":"UNIVERSIDAD DE LA SERENA","Público/Privado":"SI","Jurídico/Natural":"INSTITUCION PUBLICA","Proyecto":"INCA220011","etapa":"","Fecha de Transferencia":"2023-12-15","Numero de Cuota":"3","Monto de Transferencia":66580300.0,"Aplicaciones (Rendiciones)":61410149.0,"Reintegros":0.0,"Saldo":5170151.0,"Presentación Rendición":"8888-08-08","Vigente/Pendiente (según Rendición presentada)":"VIGENTE","Fecha Término de Proyecto":"2024-11-24","Estado según saldo (2 años del giro)":"DEUDA MOROSA"},{"Subdirección":"REDES, ESTRATEGIA Y CONOCIMIENTO (SREC)","Programa":"PCI","Cuenta":"12106031400100","Nombre Cuenta":"INES ESTATALES","Imputacion":"2403","financiamiento":"ANID","Beneficiario":"UNIVERSIDAD DE LA SERENA","Público/Privado":"SI","Jurídico/Natural":"INSTITUCION PUBLICA","Proyecto":"INGE220009","etapa":"","Fecha de Transferencia":"2023-12-15","Numero de Cuota":"3","Monto de Transferencia":143413333.0,"Aplicaciones (Rendiciones)":127388144.0,"Reintegros":0.0,"Saldo":16025189.0,"Presentación Rendición":"8888-08-08","Vigente/Pendiente (según Rendición presentada)":"VIGENTE","Fecha Término de Proyecto":"2026-11-24","Estado según saldo (2 años del giro)":"DEUDA MOROSA"},{"Subdirección":"REDES, ESTRATEGIA Y CONOCIMIENTO (SREC)","Programa":"PCI","Cuenta":"12106031400100","Nombre Cuenta":"INES ESTATALES","Imputacion":"2403","financiamiento":"ANID","Beneficiario":"UNIVERSIDAD DE LA SERENA","Público/Privado":"SI","Jurídico/Natural":"INSTITUCION PUBLICA","Proyecto":"INID230003","etapa":"","Fecha de Transferencia":"2023-11-29","Numero de Cuota":"1","Monto de Transferencia":237071667.0,"Aplicaciones (Rendiciones)":131555114.0,"Reintegros":13128121.0,"Saldo":92388432.0,"Presentación Rendición":"8888-08-08","Vigente/Pendiente (según Rendición presentada)":"VIGENTE","Fecha Término de Proyecto":"2026-11-29","Estado según saldo (2 años del giro)":"DEUDA MOROSA"},{"Subdirección":"REDES, ESTRATEGIA Y CONOCIMIENTO (SREC)","Programa":"PCI","Cuenta":"12106031701000","Nombre Cuenta":"APOYO INNOVA. E. SUP. INES I+D","Imputacion":"2403","financiamiento":"ANID","Beneficiario":"UNIVERSIDAD DE LA SERENA","Público/Privado":"SI","Jurídico/Natural":"INSTITUCION PUBLICA","Proyecto":"INID230003","etapa":"","Fecha de Transferencia":"2024-12-11","Numero de Cuota":"C3-6","Monto de Transferencia":245369175.0,"Aplicaciones (Rendiciones)":0.0,"Reintegros":0.0,"Saldo":245369175.0,"Presentación Rendición":"2026-12-22","Vigente/Pendiente (según Rendición presentada)":"VIGENTE","Fecha Término de Proyecto":"2026-11-29","Estado según saldo (2 años del giro)":"DEUDA VENCIDA"},{"Subdirección":"REDES, ESTRATEGIA Y CONOCIMIENTO (SREC)","Programa":"PCI","Cuenta":"12106031701000","Nombre Cuenta":"APOYO INNOVA. E. SUP. INES I+D","Imputacion":"2403","financiamiento":"ANID","Beneficiario":"UNIVERSIDAD DE LA SERENA","Público/Privado":"SI","Jurídico/Natural":"INSTITUCION PUBLICA","Proyecto":"INID230003","etapa":"","Fecha de Transferencia":"2025-12-10","Numero de Cuota":"C5-6","Monto de Transferencia":255674680.0,"Aplicaciones (Rendiciones)":0.0,"Reintegros":0.0,"Saldo":255674680.0,"Presentación Rendición":"2026-12-29","Vigente/Pendiente (según Rendición presentada)":"VIGENTE","Fecha Término de Proyecto":"2026-11-29","Estado según saldo (2 años del giro)":"DEUDA SIN RETRASO"},{"Subdirección":"REDES, ESTRATEGIA Y CONOCIMIENTO (SREC)","Programa":"PCI","Cuenta":"12106031702000","Nombre Cuenta":"APOYO INNOVAC E. SUP INES GENE","Imputacion":"2403","financiamiento":"ANID","Beneficiario":"UNIVERSIDAD DE LA SERENA","Público/Privado":"SI","Jurídico/Natural":"INSTITUCION PUBLICA","Proyecto":"INGE220009","etapa":"","Fecha de Transferencia":"2024-12-11","Numero de Cuota":"C5-6","Monto de Transferencia":143413333.0,"Aplicaciones (Rendiciones)":110058787.0,"Reintegros":0.0,"Saldo":33354546.0,"Presentación Rendición":"2026-09-22","Vigente/Pendiente (según Rendición presentada)":"VIGENTE","Fecha Término de Proyecto":"2026-08-20","Estado según saldo (2 años del giro)":"DEUDA VENCIDA"},{"Subdirección":"REDES, ESTRATEGIA Y CONOCIMIENTO (SREC)","Programa":"PCI","Cuenta":"12106031901000","Nombre Cuenta":"DEUDORES PCI","Imputacion":"2403","financiamiento":"ANID","Beneficiario":"UNIVERSIDAD DE LA SERENA","Público/Privado":"SI","Jurídico/Natural":"INSTITUCION PUBLICA","Proyecto":"ING2530001","etapa":"","Fecha de Transferencia":"2025-11-30","Numero de Cuota":"C1-3","Monto de Transferencia":333333333.0,"Aplicaciones (Rendiciones)":0.0,"Reintegros":0.0,"Saldo":333333333.0,"Presentación Rendición":"2026-12-30","Vigente/Pendiente (según Rendición presentada)":"VIGENTE","Fecha Término de Proyecto":"2028-10-29","Estado según saldo (2 años del giro)":"DEUDA SIN RETRASO"},{"Subdirección":"REDES, ESTRATEGIA Y CONOCIMIENTO (SREC)","Programa":"PCI","Cuenta":"12106032401000","Nombre Cuenta":"DEUDORES FIU","Imputacion":"2403","financiamiento":"CAPACIDADES TECNOLOGICAS","Beneficiario":"UNIVERSIDAD DE LA SERENA","Público/Privado":"SI","Jurídico/Natural":"INSTITUCION PUBLICA","Proyecto":"136753","etapa":"","Fecha de Transferencia":"2025-12-31","Numero de Cuota":"C1-11","Monto de Transferencia":260000000.0,"Aplicaciones (Rendiciones)":0.0,"Reintegros":0.0,"Saldo":260000000.0,"Presentación Rendición":"2027-01-30","Vigente/Pendiente (según Rendición presentada)":"VIGENTE","Fecha Término de Proyecto":"2035-12-30","Estado según saldo (2 años del giro)":"DEUDA SIN RETRASO"},{"Subdirección":"CENTROS E INVESTIGACIÓN ASOCIATIVA (SCIA)","Programa":"FONDEQUIP","Cuenta":"12106040102000","Nombre Cuenta":"Equipamiento Mayor","Imputacion":"3303","financiamiento":"ANID","Beneficiario":"UNIVERSIDAD DE LA SERENA","Público/Privado":"SI","Jurídico/Natural":"INSTITUCION PUBLICA","Proyecto":"EQY220026","etapa":"","Fecha de Transferencia":"2022-12-22","Numero de Cuota":"1","Monto de Transferencia":877972159.0,"Aplicaciones (Rendiciones)":398850474.0,"Reintegros":0.0,"Saldo":479121685.0,"Presentación Rendición":"2026-10-22","Vigente/Pendiente (según Rendición presentada)":"VIGENTE","Fecha Término de Proyecto":"2026-09-22","Estado según saldo (2 años del giro)":"DEUDA MOROSA"},{"Subdirección":"REDES, ESTRATEGIA Y CONOCIMIENTO (SREC)","Programa":"PCI","Cuenta":"12106041200100","Nombre Cuenta":"INES ESTATALES","Imputacion":"3303","financiamiento":"ANID","Beneficiario":"UNIVERSIDAD DE LA SERENA","Público/Privado":"SI","Jurídico/Natural":"INSTITUCION PUBLICA","Proyecto":"INCA220011","etapa":"","Fecha de Transferencia":"2023-12-15","Numero de Cuota":"4","Monto de Transferencia":28305000.0,"Aplicaciones (Rendiciones)":24534549.0,"Reintegros":0.0,"Saldo":3770451.0,"Presentación Rendición":"8888-08-08","Vigente/Pendiente (según Rendición presentada)":"VIGENTE","Fecha Término de Proyecto":"2024-11-24","Estado según saldo (2 años del giro)":"DEUDA MOROSA"},{"Subdirección":"REDES, ESTRATEGIA Y CONOCIMIENTO (SREC)","Programa":"PCI","Cuenta":"12106041200100","Nombre Cuenta":"INES ESTATALES","Imputacion":"3303","financiamiento":"ANID","Beneficiario":"UNIVERSIDAD DE LA SERENA","Público/Privado":"SI","Jurídico/Natural":"INSTITUCION PUBLICA","Proyecto":"INGE220009","etapa":"","Fecha de Transferencia":"2023-12-15","Numero de Cuota":"4","Monto de Transferencia":6316667.0,"Aplicaciones (Rendiciones)":6268332.0,"Reintegros":0.0,"Saldo":48335.0,"Presentación Rendición":"2026-01-15","Vigente/Pendiente (según Rendición presentada)":"PENDIENTE","Fecha Término de Proyecto":"2026-11-24","Estado según saldo (2 años del giro)":"DEUDA MOROSA"},{"Subdirección":"REDES, ESTRATEGIA Y CONOCIMIENTO (SREC)","Programa":"PCI","Cuenta":"12106041200100","Nombre Cuenta":"INES ESTATALES","Imputacion":"3303","financiamiento":"ANID","Beneficiario":"UNIVERSIDAD DE LA SERENA","Público/Privado":"SI","Jurídico/Natural":"INSTITUCION PUBLICA","Proyecto":"INID230003","etapa":"","Fecha de Transferencia":"2023-11-29","Numero de Cuota":"2","Monto de Transferencia":89833333.0,"Aplicaciones (Rendiciones)":44950118.0,"Reintegros":787251.0,"Saldo":44095964.0,"Presentación Rendición":"8888-08-08","Vigente/Pendiente (según Rendición presentada)":"VIGENTE","Fecha Término de Proyecto":"2026-11-29","Estado según saldo (2 años del giro)":"DEUDA MOROSA"},{"Subdirección":"REDES, ESTRATEGIA Y CONOCIMIENTO (SREC)","Programa":"PCI","Cuenta":"12106041401000","Nombre Cuenta":"APOYO INNOVA EDUC. SUP I+D","Imputacion":"3303","financiamiento":"ANID","Beneficiario":"UNIVERSIDAD DE LA SERENA","Público/Privado":"SI","Jurídico/Natural":"INSTITUCION PUBLICA","Proyecto":"INID230003","etapa":"","Fecha de Transferencia":"2024-12-11","Numero de Cuota":"C4-6","Monto de Transferencia":92977500.0,"Aplicaciones (Rendiciones)":0.0,"Reintegros":0.0,"Saldo":92977500.0,"Presentación Rendición":"2026-12-22","Vigente/Pendiente (según Rendición presentada)":"VIGENTE","Fecha Término de Proyecto":"2026-11-29","Estado según saldo (2 años del giro)":"DEUDA VENCIDA"},{"Subdirección":"REDES, ESTRATEGIA Y CONOCIMIENTO (SREC)","Programa":"PCI","Cuenta":"12106041401000","Nombre Cuenta":"APOYO INNOVA EDUC. SUP I+D","Imputacion":"3303","financiamiento":"ANID","Beneficiario":"UNIVERSIDAD DE LA SERENA","Público/Privado":"SI","Jurídico/Natural":"INSTITUCION PUBLICA","Proyecto":"INID230003","etapa":"","Fecha de Transferencia":"2025-12-10","Numero de Cuota":"C6-6","Monto de Transferencia":96882555.0,"Aplicaciones (Rendiciones)":0.0,"Reintegros":0.0,"Saldo":96882555.0,"Presentación Rendición":"2026-12-29","Vigente/Pendiente (según Rendición presentada)":"VIGENTE","Fecha Término de Proyecto":"2026-11-29","Estado según saldo (2 años del giro)":"DEUDA SIN RETRASO"},{"Subdirección":"REDES, ESTRATEGIA Y CONOCIMIENTO (SREC)","Programa":"PCI","Cuenta":"12106041402000","Nombre Cuenta":"APOYO INNOVA. ED.SUP. INES GEN","Imputacion":"3303","financiamiento":"ANID","Beneficiario":"UNIVERSIDAD DE LA SERENA","Público/Privado":"SI","Jurídico/Natural":"INSTITUCION PUBLICA","Proyecto":"INGE220009","etapa":"","Fecha de Transferencia":"2024-12-11","Numero de Cuota":"C6-6","Monto de Transferencia":6316667.0,"Aplicaciones (Rendiciones)":1072178.0,"Reintegros":0.0,"Saldo":5244489.0,"Presentación Rendición":"2026-09-22","Vigente/Pendiente (según Rendición presentada)":"VIGENTE","Fecha Término de Proyecto":"2026-08-20","Estado según saldo (2 años del giro)":"DEUDA VENCIDA"},{"Subdirección":"INVESTIGACIÓN APLICADA (SIA)","Programa":"FONDEF","Cuenta":"12402010000000","Nombre Cuenta":"Deudores Cobranza Adm. y recopilacion de antecedentes","Imputacion":"0","financiamiento":"ANID","Beneficiario":"UNIVERSIDAD DE LA SERENA","Público/Privado":"SI","Jurídico/Natural":"INSTITUCION PUBLICA","Proyecto":"ID21I10374","etapa":"","Fecha de Transferencia":"2022-01-19","Numero de Cuota":"1","Monto de Transferencia":199919000.0,"Aplicaciones (Rendiciones)":181832081.0,"Reintegros":656455.0,"Saldo":17430464.0,"Presentación Rendición":"8888-08-08","Vigente/Pendiente (según Rendición presentada)":"VIGENTE","Fecha Término de Proyecto":"2024-04-16","Estado según saldo (2 años del giro)":"DEUDA MOROSA"},{"Subdirección":"REDES, ESTRATEGIA Y CONOCIMIENTO (SREC)","Programa":"PCI","Cuenta":"12402010000000","Nombre Cuenta":"Deudores Cobranza Adm. y recopilacion de antecedentes","Imputacion":"0","financiamiento":"ANID","Beneficiario":"UNIVERSIDAD DE LA SERENA","Público/Privado":"SI","Jurídico/Natural":"INSTITUCION PUBLICA","Proyecto":"INCA220011","etapa":"","Fecha de Transferencia":"2022-11-24","Numero de Cuota":"1","Monto de Transferencia":66580300.0,"Aplicaciones (Rendiciones)":66367964.0,"Reintegros":0.0,"Saldo":212336.0,"Presentación Rendición":"8888-08-08","Vigente/Pendiente (según Rendición presentada)":"VIGENTE","Fecha Término de Proyecto":"2024-11-24","Estado según saldo (2 años del giro)":"DEUDA MOROSA"},{"Subdirección":"REDES, ESTRATEGIA Y CONOCIMIENTO (SREC)","Programa":"PCI","Cuenta":"12402010000000","Nombre Cuenta":"Deudores Cobranza Adm. y recopilacion de antecedentes","Imputacion":"0","financiamiento":"ANID","Beneficiario":"UNIVERSIDAD DE LA SERENA","Público/Privado":"SI","Jurídico/Natural":"INSTITUCION PUBLICA","Proyecto":"INCA220011","etapa":"","Fecha de Transferencia":"2022-11-24","Numero de Cuota":"2","Monto de Transferencia":28305000.0,"Aplicaciones (Rendiciones)":27676284.0,"Reintegros":0.0,"Saldo":628716.0,"Presentación Rendición":"8888-08-08","Vigente/Pendiente (según Rendición presentada)":"VIGENTE","Fecha Término de Proyecto":"2024-11-24","Estado según saldo (2 años del giro)":"DEUDA MOROSA"},{"Subdirección":"REDES, ESTRATEGIA Y CONOCIMIENTO (SREC)","Programa":"PCI","Cuenta":"12402010000000","Nombre Cuenta":"Deudores Cobranza Adm. y recopilacion de antecedentes","Imputacion":"0","financiamiento":"ANID","Beneficiario":"UNIVERSIDAD DE LA SERENA","Público/Privado":"SI","Jurídico/Natural":"INSTITUCION PUBLICA","Proyecto":"INGE220009","etapa":"","Fecha de Transferencia":"2022-11-24","Numero de Cuota":"2","Monto de Transferencia":6316667.0,"Aplicaciones (Rendiciones)":5548760.0,"Reintegros":0.0,"Saldo":767907.0,"Presentación Rendición":"8888-08-08","Vigente/Pendiente (según Rendición presentada)":"VIGENTE","Fecha Término de Proyecto":"2026-11-24","Estado según saldo (2 años del giro)":"DEUDA MOROSA"},{"Subdirección":"REDES, ESTRATEGIA Y CONOCIMIENTO (SREC)","Programa":"PCI","Cuenta":"12402010000000","Nombre Cuenta":"Deudores Cobranza Adm. y recopilacion de antecedentes","Imputacion":"0","financiamiento":"ANID","Beneficiario":"UNIVERSIDAD DE LA SERENA","Público/Privado":"SI","Jurídico/Natural":"INSTITUCION PUBLICA","Proyecto":"INGE220009","etapa":"","Fecha de Transferencia":"2022-11-24","Numero de Cuota":"1","Monto de Transferencia":143413333.0,"Aplicaciones (Rendiciones)":133385999.0,"Reintegros":0.0,"Saldo":10027334.0,"Presentación Rendición":"8888-08-08","Vigente/Pendiente (según Rendición presentada)":"VIGENTE","Fecha Término de Proyecto":"2026-11-24","Estado según saldo (2 años del giro)":"DEUDA MOROSA"},{"Subdirección":"REDES, ESTRATEGIA Y CONOCIMIENTO (SREC)","Programa":"ASTRONOMIA","Cuenta":"12402010000000","Nombre Cuenta":"Deudores Cobranza Adm. y recopilacion de antecedentes","Imputacion":"0","financiamiento":"ANID","Beneficiario":"UNIVERSIDAD DE LA SERENA","Público/Privado":"SI","Jurídico/Natural":"INSTITUCION PUBLICA","Proyecto":"QUIMAL220008","etapa":"","Fecha de Transferencia":"2023-12-22","Numero de Cuota":"2","Monto de Transferencia":89192000.0,"Aplicaciones (Rendiciones)":20589091.0,"Reintegros":0.0,"Saldo":68602909.0,"Presentación Rendición":"8888-08-08","Vigente/Pendiente (según Rendición presentada)":"VIGENTE","Fecha Término de Proyecto":"2025-12-21","Estado según saldo (2 años del giro)":"DEUDA MOROSA"},{"Subdirección":"REDES, ESTRATEGIA Y CONOCIMIENTO (SREC)","Programa":"ASTRONOMIA","Cuenta":"12402010000000","Nombre Cuenta":"Deudores Cobranza Adm. y recopilacion de antecedentes","Imputacion":"0","financiamiento":"ANID","Beneficiario":"UNIVERSIDAD DE LA SERENA","Público/Privado":"SI","Jurídico/Natural":"INSTITUCION PUBLICA","Proyecto":"QUIMAL220008","etapa":"","Fecha de Transferencia":"2022-12-30","Numero de Cuota":"1","Monto de Transferencia":76688000.0,"Aplicaciones (Rendiciones)":68793727.0,"Reintegros":0.0,"Saldo":7894273.0,"Presentación Rendición":"8888-08-08","Vigente/Pendiente (según Rendición presentada)":"VIGENTE","Fecha Término de Proyecto":"2025-12-21","Estado según saldo (2 años del giro)":"DEUDA MOROSA"}]}