{"institucion":"UNIVERSIDAD DE MAGALLANES","fecha_corte":"2026-07-19","resumen":{"saldo_total":2401203473.0,"monto_transferido_total":4596922350.0,"rendido_total":2188622890.0,"porcentaje_rendido":47.6,"cuotas_con_deuda":62,"por_estado_morosidad":{"DEUDA VENCIDA":24,"DEUDA MOROSA":19,"DEUDA SIN RETRASO":19}},"proximos_vencimientos":[{"Subdirección":"INVESTIGACIÓN APLICADA (SIA)","Programa":"FONDEF","Cuenta":"12106030220000","Nombre Cuenta":"Deudores Concurso Investigar para Crear","Imputacion":"2403","financiamiento":"ANID","Beneficiario":"UNIVERSIDAD DE MAGALLANES","Público/Privado":"SI","Jurídico/Natural":"INSTITUCION PUBLICA","Proyecto":"VIU24P0022","etapa":"","Fecha de Transferencia":"2024-11-15","Numero de Cuota":"C1-1","Monto de Transferencia":36000000.0,"Aplicaciones (Rendiciones)":28542181.0,"Reintegros":0.0,"Saldo":7457819.0,"Presentación Rendición":"2026-06-22","Vigente/Pendiente (según Rendición presentada)":"PENDIENTE","Fecha Término de Proyecto":"2026-05-11","Estado según saldo (2 años del giro)":"DEUDA VENCIDA"}],"detalle":[{"Subdirección":"CAPITAL HUMANO (SCH)","Programa":"CHA","Cuenta":"12106010234000","Nombre Cuenta":"Fortalecimiento programa de doctorado","Imputacion":"2401","financiamiento":"ANID","Beneficiario":"UNIVERSIDAD DE MAGALLANES","Público/Privado":"SI","Jurídico/Natural":"INSTITUCION PUBLICA","Proyecto":"86220036","etapa":"","Fecha de Transferencia":"2025-06-23","Numero de Cuota":"C3-3","Monto de Transferencia":86206120.0,"Aplicaciones (Rendiciones)":32835827.0,"Reintegros":0.0,"Saldo":53370293.0,"Presentación Rendición":"8888-08-08","Vigente/Pendiente (según Rendición presentada)":"VIGENTE","Fecha Término de Proyecto":"2026-10-31","Estado según saldo (2 años del giro)":"DEUDA VENCIDA"},{"Subdirección":"CAPITAL HUMANO (SCH)","Programa":"CHA","Cuenta":"12106010234000","Nombre Cuenta":"Fortalecimiento programa de doctorado","Imputacion":"2401","financiamiento":"ANID","Beneficiario":"UNIVERSIDAD DE MAGALLANES","Público/Privado":"SI","Jurídico/Natural":"INSTITUCION PUBLICA","Proyecto":"86220036","etapa":"","Fecha de Transferencia":"2024-10-14","Numero de Cuota":"C2-3","Monto de Transferencia":86206120.0,"Aplicaciones (Rendiciones)":35929000.0,"Reintegros":0.0,"Saldo":50277120.0,"Presentación Rendición":"8888-08-08","Vigente/Pendiente (según Rendición presentada)":"VIGENTE","Fecha Término de Proyecto":"2026-10-31","Estado según saldo (2 años del giro)":"DEUDA VENCIDA"},{"Subdirección":"CAPITAL HUMANO (SCH)","Programa":"CHA","Cuenta":"12106010901000","Nombre Cuenta":"Deudores Insercion de Inve. Academia","Imputacion":"2401","financiamiento":"ANID","Beneficiario":"UNIVERSIDAD DE MAGALLANES","Público/Privado":"SI","Jurídico/Natural":"INSTITUCION PUBLICA","Proyecto":"85220004","etapa":"","Fecha de Transferencia":"2024-12-26","Numero de Cuota":"C3-3","Monto de Transferencia":51513000.0,"Aplicaciones (Rendiciones)":50823000.0,"Reintegros":0.0,"Saldo":690000.0,"Presentación Rendición":"8888-08-08","Vigente/Pendiente (según Rendición presentada)":"VIGENTE","Fecha Término de Proyecto":"2025-12-31","Estado según saldo (2 años del giro)":"DEUDA VENCIDA"},{"Subdirección":"CAPITAL HUMANO (SCH)","Programa":"CHA","Cuenta":"12106010901000","Nombre Cuenta":"Deudores Insercion de Inve. Academia","Imputacion":"2401","financiamiento":"ANID","Beneficiario":"UNIVERSIDAD DE MAGALLANES","Público/Privado":"SI","Jurídico/Natural":"INSTITUCION PUBLICA","Proyecto":"85220004","etapa":"","Fecha de Transferencia":"2023-11-27","Numero de Cuota":"2","Monto de Transferencia":51513000.0,"Aplicaciones (Rendiciones)":47239332.0,"Reintegros":0.0,"Saldo":4273668.0,"Presentación Rendición":"8888-08-08","Vigente/Pendiente (según Rendición presentada)":"VIGENTE","Fecha Término de Proyecto":"2025-12-31","Estado según saldo (2 años del giro)":"DEUDA MOROSA"},{"Subdirección":"CAPITAL HUMANO (SCH)","Programa":"CHA","Cuenta":"12106010901000","Nombre Cuenta":"Deudores Insercion de Inve. Academia","Imputacion":"2401","financiamiento":"ANID","Beneficiario":"UNIVERSIDAD DE MAGALLANES","Público/Privado":"SI","Jurídico/Natural":"INSTITUCION PUBLICA","Proyecto":"85220032","etapa":"","Fecha de Transferencia":"2024-12-26","Numero de Cuota":"C3-3","Monto de Transferencia":51663334.0,"Aplicaciones (Rendiciones)":47850050.0,"Reintegros":0.0,"Saldo":3813284.0,"Presentación Rendición":"8888-08-08","Vigente/Pendiente (según Rendición presentada)":"VIGENTE","Fecha Término de Proyecto":"2026-01-31","Estado según saldo (2 años del giro)":"DEUDA VENCIDA"},{"Subdirección":"CAPITAL HUMANO (SCH)","Programa":"CHA","Cuenta":"12106010901000","Nombre Cuenta":"Deudores Insercion de Inve. Academia","Imputacion":"2401","financiamiento":"ANID","Beneficiario":"UNIVERSIDAD DE MAGALLANES","Público/Privado":"SI","Jurídico/Natural":"INSTITUCION PUBLICA","Proyecto":"85220121","etapa":"","Fecha de Transferencia":"2024-12-26","Numero de Cuota":"C3-3","Monto de Transferencia":66725515.0,"Aplicaciones (Rendiciones)":48048827.0,"Reintegros":0.0,"Saldo":18676688.0,"Presentación Rendición":"8888-08-08","Vigente/Pendiente (según Rendición presentada)":"VIGENTE","Fecha Término de Proyecto":"2026-09-28","Estado según saldo (2 años del giro)":"DEUDA VENCIDA"},{"Subdirección":"CAPITAL HUMANO (SCH)","Programa":"CHA","Cuenta":"12106010901000","Nombre Cuenta":"Deudores Insercion de Inve. Academia","Imputacion":"2401","financiamiento":"ANID","Beneficiario":"UNIVERSIDAD DE MAGALLANES","Público/Privado":"SI","Jurídico/Natural":"INSTITUCION PUBLICA","Proyecto":"85240061","etapa":"","Fecha de Transferencia":"2024-10-10","Numero de Cuota":"C1-3","Monto de Transferencia":67594400.0,"Aplicaciones (Rendiciones)":67575405.0,"Reintegros":0.0,"Saldo":18995.0,"Presentación Rendición":"8888-08-08","Vigente/Pendiente (según Rendición presentada)":"VIGENTE","Fecha Término de Proyecto":"2027-07-22","Estado según saldo (2 años del giro)":"DEUDA VENCIDA"},{"Subdirección":"CAPITAL HUMANO (SCH)","Programa":"CHA","Cuenta":"12106010901000","Nombre Cuenta":"Deudores Insercion de Inve. Academia","Imputacion":"2401","financiamiento":"ANID","Beneficiario":"UNIVERSIDAD DE MAGALLANES","Público/Privado":"SI","Jurídico/Natural":"INSTITUCION PUBLICA","Proyecto":"85240139","etapa":"","Fecha de Transferencia":"2024-10-10","Numero de Cuota":"C1-3","Monto de Transferencia":70720000.0,"Aplicaciones (Rendiciones)":69608206.0,"Reintegros":0.0,"Saldo":1111794.0,"Presentación Rendición":"2027-08-23","Vigente/Pendiente (según Rendición presentada)":"VIGENTE","Fecha Término de Proyecto":"2027-07-22","Estado según saldo (2 años del giro)":"DEUDA VENCIDA"},{"Subdirección":"INVESTIGACIÓN APLICADA (SIA)","Programa":"FONDEF","Cuenta":"12106012400100","Nombre Cuenta":"FORTALECIMIENTO OTL 2.0 Y OTL","Imputacion":"2401","financiamiento":"ANID","Beneficiario":"UNIVERSIDAD DE MAGALLANES","Público/Privado":"SI","Jurídico/Natural":"INSTITUCION PUBLICA","Proyecto":"OTL220014","etapa":"","Fecha de Transferencia":"2024-12-27","Numero de Cuota":"C3-4","Monto de Transferencia":60000000.0,"Aplicaciones (Rendiciones)":0.0,"Reintegros":0.0,"Saldo":60000000.0,"Presentación Rendición":"2026-11-20","Vigente/Pendiente (según Rendición presentada)":"VIGENTE","Fecha Término de Proyecto":"2026-10-25","Estado según saldo (2 años del giro)":"DEUDA VENCIDA"},{"Subdirección":"PROYECTOS DE INVESTIGACIÓN (SPI)","Programa":"FONDECYT","Cuenta":"12106030103000","Nombre Cuenta":"Deudores Regular Institución","Imputacion":"2403","financiamiento":"ANID","Beneficiario":"UNIVERSIDAD DE MAGALLANES","Público/Privado":"SI","Jurídico/Natural":"INSTITUCION PUBLICA","Proyecto":"1240133","etapa":"2025 GA","Fecha de Transferencia":"2025-12-31","Numero de Cuota":"C2-4-2","Monto de Transferencia":396000.0,"Aplicaciones (Rendiciones)":0.0,"Reintegros":0.0,"Saldo":396000.0,"Presentación Rendición":"2027-01-22","Vigente/Pendiente (según Rendición presentada)":"VIGENTE","Fecha Término de Proyecto":"2028-03-31","Estado según saldo (2 años del giro)":"DEUDA SIN RETRASO"},{"Subdirección":"PROYECTOS DE INVESTIGACIÓN (SPI)","Programa":"FONDECYT","Cuenta":"12106030103000","Nombre Cuenta":"Deudores Regular Institución","Imputacion":"2403","financiamiento":"ANID","Beneficiario":"UNIVERSIDAD DE MAGALLANES","Público/Privado":"SI","Jurídico/Natural":"INSTITUCION PUBLICA","Proyecto":"1240135","etapa":"2025 GA","Fecha de Transferencia":"2025-12-31","Numero de Cuota":"C2-4-2","Monto de Transferencia":308000.0,"Aplicaciones (Rendiciones)":0.0,"Reintegros":0.0,"Saldo":308000.0,"Presentación Rendición":"2027-01-22","Vigente/Pendiente (según Rendición presentada)":"VIGENTE","Fecha Término de Proyecto":"2028-03-31","Estado según saldo (2 años del giro)":"DEUDA SIN RETRASO"},{"Subdirección":"PROYECTOS DE INVESTIGACIÓN (SPI)","Programa":"FONDECYT","Cuenta":"12106030103000","Nombre Cuenta":"Deudores Regular Institución","Imputacion":"2403","financiamiento":"ANID","Beneficiario":"UNIVERSIDAD DE MAGALLANES","Público/Privado":"SI","Jurídico/Natural":"INSTITUCION PUBLICA","Proyecto":"1241391","etapa":"2025 GA","Fecha de Transferencia":"2025-12-31","Numero de Cuota":"C2-4-2","Monto de Transferencia":339000.0,"Aplicaciones (Rendiciones)":0.0,"Reintegros":0.0,"Saldo":339000.0,"Presentación Rendición":"2027-01-22","Vigente/Pendiente (según Rendición presentada)":"VIGENTE","Fecha Término de Proyecto":"2028-03-31","Estado según saldo (2 años del giro)":"DEUDA SIN RETRASO"},{"Subdirección":"PROYECTOS DE INVESTIGACIÓN (SPI)","Programa":"FONDECYT","Cuenta":"12106030103000","Nombre Cuenta":"Deudores Regular Institución","Imputacion":"2403","financiamiento":"ANID","Beneficiario":"UNIVERSIDAD DE MAGALLANES","Público/Privado":"SI","Jurídico/Natural":"INSTITUCION PUBLICA","Proyecto":"1241697","etapa":"2025 GA","Fecha de Transferencia":"2025-12-31","Numero de Cuota":"C2-4-2","Monto de Transferencia":292000.0,"Aplicaciones (Rendiciones)":0.0,"Reintegros":0.0,"Saldo":292000.0,"Presentación Rendición":"2027-01-22","Vigente/Pendiente (según Rendición presentada)":"VIGENTE","Fecha Término de Proyecto":"2028-03-31","Estado según saldo (2 años del giro)":"DEUDA SIN RETRASO"},{"Subdirección":"PROYECTOS DE INVESTIGACIÓN (SPI)","Programa":"FONDECYT","Cuenta":"12106030105000","Nombre Cuenta":"Deudores Regular Iniciación Bienes de Capital ","Imputacion":"2403","financiamiento":"ANID","Beneficiario":"UNIVERSIDAD DE MAGALLANES","Público/Privado":"SI","Jurídico/Natural":"INSTITUCION PUBLICA","Proyecto":"11240506","etapa":"2025 GA","Fecha de Transferencia":"2025-06-30","Numero de Cuota":"C2-3-1","Monto de Transferencia":3450000.0,"Aplicaciones (Rendiciones)":0.0,"Reintegros":0.0,"Saldo":3450000.0,"Presentación Rendición":"8888-08-08","Vigente/Pendiente (según Rendición presentada)":"VIGENTE","Fecha Término de Proyecto":"2027-03-14","Estado según saldo (2 años del giro)":"DEUDA VENCIDA"},{"Subdirección":"PROYECTOS DE INVESTIGACIÓN (SPI)","Programa":"FONDECYT","Cuenta":"12106030105000","Nombre Cuenta":"Deudores Regular Iniciación Bienes de Capital ","Imputacion":"2403","financiamiento":"ANID","Beneficiario":"UNIVERSIDAD DE MAGALLANES","Público/Privado":"SI","Jurídico/Natural":"INSTITUCION PUBLICA","Proyecto":"11240506","etapa":"2025 GA","Fecha de Transferencia":"2025-12-31","Numero de Cuota":"C2-3-2","Monto de Transferencia":144000.0,"Aplicaciones (Rendiciones)":0.0,"Reintegros":0.0,"Saldo":144000.0,"Presentación Rendición":"2027-01-22","Vigente/Pendiente (según Rendición presentada)":"VIGENTE","Fecha Término de Proyecto":"2027-03-14","Estado según saldo (2 años del giro)":"DEUDA SIN RETRASO"},{"Subdirección":"PROYECTOS DE INVESTIGACIÓN (SPI)","Programa":"FONDECYT","Cuenta":"12106030105000","Nombre Cuenta":"Deudores Regular Iniciación Bienes de Capital ","Imputacion":"2403","financiamiento":"ANID","Beneficiario":"UNIVERSIDAD DE MAGALLANES","Público/Privado":"SI","Jurídico/Natural":"INSTITUCION PUBLICA","Proyecto":"11241322","etapa":"2025 GA","Fecha de Transferencia":"2025-12-31","Numero de Cuota":"C2-3-2","Monto de Transferencia":240000.0,"Aplicaciones (Rendiciones)":0.0,"Reintegros":0.0,"Saldo":240000.0,"Presentación Rendición":"2027-01-22","Vigente/Pendiente (según Rendición presentada)":"VIGENTE","Fecha Término de Proyecto":"2027-03-14","Estado según saldo (2 años del giro)":"DEUDA SIN RETRASO"},{"Subdirección":"PROYECTOS DE INVESTIGACIÓN (SPI)","Programa":"FONDECYT","Cuenta":"12106030105000","Nombre Cuenta":"Deudores Regular Iniciación Bienes de Capital ","Imputacion":"2403","financiamiento":"ANID","Beneficiario":"UNIVERSIDAD DE MAGALLANES","Público/Privado":"SI","Jurídico/Natural":"INSTITUCION PUBLICA","Proyecto":"11241322","etapa":"2025 GA","Fecha de Transferencia":"2025-06-30","Numero de Cuota":"C2-3-1","Monto de Transferencia":5725000.0,"Aplicaciones (Rendiciones)":0.0,"Reintegros":0.0,"Saldo":5725000.0,"Presentación Rendición":"8888-08-08","Vigente/Pendiente (según Rendición presentada)":"VIGENTE","Fecha Término de Proyecto":"2027-03-14","Estado según saldo (2 años del giro)":"DEUDA VENCIDA"},{"Subdirección":"PROYECTOS DE INVESTIGACIÓN (SPI)","Programa":"FONDECYT","Cuenta":"12106030105000","Nombre Cuenta":"Deudores Regular Iniciación Bienes de Capital ","Imputacion":"2403","financiamiento":"ANID","Beneficiario":"UNIVERSIDAD DE MAGALLANES","Público/Privado":"SI","Jurídico/Natural":"INSTITUCION PUBLICA","Proyecto":"11250295","etapa":"2025 GA","Fecha de Transferencia":"2025-06-30","Numero de Cuota":"C1-3-1","Monto de Transferencia":4800000.0,"Aplicaciones (Rendiciones)":0.0,"Reintegros":0.0,"Saldo":4800000.0,"Presentación Rendición":"8888-08-08","Vigente/Pendiente (según Rendición presentada)":"VIGENTE","Fecha Término de Proyecto":"2028-03-31","Estado según saldo (2 años del giro)":"DEUDA VENCIDA"},{"Subdirección":"INVESTIGACIÓN APLICADA (SIA)","Programa":"FONDEF","Cuenta":"12106030201000","Nombre Cuenta":"DEUDORES FONDEF ID","Imputacion":"2403","financiamiento":"ANID","Beneficiario":"UNIVERSIDAD DE MAGALLANES","Público/Privado":"SI","Jurídico/Natural":"INSTITUCION PUBLICA","Proyecto":"ID24I10045","etapa":"","Fecha de Transferencia":"2025-06-26","Numero de Cuota":"C2-2","Monto de Transferencia":118329728.0,"Aplicaciones (Rendiciones)":30814463.0,"Reintegros":0.0,"Saldo":87515265.0,"Presentación Rendición":"2027-01-21","Vigente/Pendiente (según Rendición presentada)":"VIGENTE","Fecha Término de Proyecto":"2026-12-21","Estado según saldo (2 años del giro)":"DEUDA VENCIDA"},{"Subdirección":"INVESTIGACIÓN APLICADA (SIA)","Programa":"FONDEF","Cuenta":"12106030203000","Nombre Cuenta":"Deudores Fondef Marea Roja","Imputacion":"2403","financiamiento":"ANID","Beneficiario":"UNIVERSIDAD DE MAGALLANES","Público/Privado":"SI","Jurídico/Natural":"INSTITUCION PUBLICA","Proyecto":"TA23I10057","etapa":"","Fecha de Transferencia":"2025-12-29","Numero de Cuota":"C3-4","Monto de Transferencia":171881156.0,"Aplicaciones (Rendiciones)":0.0,"Reintegros":0.0,"Saldo":171881156.0,"Presentación Rendición":"2027-01-22","Vigente/Pendiente (según Rendición presentada)":"VIGENTE","Fecha Término de Proyecto":"2027-11-07","Estado según saldo (2 años del giro)":"DEUDA SIN RETRASO"},{"Subdirección":"INVESTIGACIÓN APLICADA (SIA)","Programa":"FONIS","Cuenta":"12106030204000","Nombre Cuenta":"Deudores Fondef Fonis","Imputacion":"2403","financiamiento":"ANID","Beneficiario":"UNIVERSIDAD DE MAGALLANES","Público/Privado":"SI","Jurídico/Natural":"INSTITUCION PUBLICA","Proyecto":"SA22I0135","etapa":"","Fecha de Transferencia":"2023-12-27","Numero de Cuota":"2","Monto de Transferencia":29995000.0,"Aplicaciones (Rendiciones)":27309206.0,"Reintegros":767141.0,"Saldo":1918653.0,"Presentación Rendición":"8888-08-08","Vigente/Pendiente (según Rendición presentada)":"VIGENTE","Fecha Término de Proyecto":"2025-11-06","Estado según saldo (2 años del giro)":"DEUDA MOROSA"},{"Subdirección":"INVESTIGACIÓN APLICADA (SIA)","Programa":"FONDEF","Cuenta":"12106030205000","Nombre Cuenta":"Deudores Fondef Tic Edu","Imputacion":"2403","financiamiento":"ANID","Beneficiario":"UNIVERSIDAD DE MAGALLANES","Público/Privado":"SI","Jurídico/Natural":"INSTITUCION PUBLICA","Proyecto":"IT25I0050","etapa":"","Fecha de Transferencia":"2025-10-23","Numero de Cuota":"C1-2","Monto de Transferencia":118500000.0,"Aplicaciones (Rendiciones)":0.0,"Reintegros":0.0,"Saldo":118500000.0,"Presentación Rendición":"2026-11-29","Vigente/Pendiente (según Rendición presentada)":"VIGENTE","Fecha Término de Proyecto":"2027-10-29","Estado según saldo (2 años del giro)":"DEUDA SIN RETRASO"},{"Subdirección":"INVESTIGACIÓN APLICADA (SIA)","Programa":"FONDEF","Cuenta":"12106030220000","Nombre Cuenta":"Deudores Concurso Investigar para Crear","Imputacion":"2403","financiamiento":"ANID","Beneficiario":"UNIVERSIDAD DE MAGALLANES","Público/Privado":"SI","Jurídico/Natural":"INSTITUCION PUBLICA","Proyecto":"VIU24P0019","etapa":"","Fecha de Transferencia":"2024-11-15","Numero de Cuota":"C1-1","Monto de Transferencia":35907000.0,"Aplicaciones (Rendiciones)":11997585.0,"Reintegros":0.0,"Saldo":23909415.0,"Presentación Rendición":"8888-08-08","Vigente/Pendiente (según Rendición presentada)":"VIGENTE","Fecha Término de Proyecto":"2026-05-05","Estado según saldo (2 años del giro)":"DEUDA VENCIDA"},{"Subdirección":"INVESTIGACIÓN APLICADA (SIA)","Programa":"FONDEF","Cuenta":"12106030220000","Nombre Cuenta":"Deudores Concurso Investigar para Crear","Imputacion":"2403","financiamiento":"ANID","Beneficiario":"UNIVERSIDAD DE MAGALLANES","Público/Privado":"SI","Jurídico/Natural":"INSTITUCION PUBLICA","Proyecto":"VIU24P0022","etapa":"","Fecha de Transferencia":"2024-11-15","Numero de Cuota":"C1-1","Monto de Transferencia":36000000.0,"Aplicaciones (Rendiciones)":28542181.0,"Reintegros":0.0,"Saldo":7457819.0,"Presentación Rendición":"2026-06-22","Vigente/Pendiente (según Rendición presentada)":"PENDIENTE","Fecha Término de Proyecto":"2026-05-11","Estado según saldo (2 años del giro)":"DEUDA VENCIDA"},{"Subdirección":"INVESTIGACIÓN APLICADA (SIA)","Programa":"FONDEF","Cuenta":"12106030220000","Nombre Cuenta":"Deudores Concurso Investigar para Crear","Imputacion":"2403","financiamiento":"ANID","Beneficiario":"UNIVERSIDAD DE MAGALLANES","Público/Privado":"SI","Jurídico/Natural":"INSTITUCION PUBLICA","Proyecto":"VIU24P0204","etapa":"","Fecha de Transferencia":"2024-11-15","Numero de Cuota":"C1-1","Monto de Transferencia":35953000.0,"Aplicaciones (Rendiciones)":17498630.0,"Reintegros":0.0,"Saldo":18454370.0,"Presentación Rendición":"2026-12-22","Vigente/Pendiente (según Rendición presentada)":"VIGENTE","Fecha Término de Proyecto":"2026-11-06","Estado según saldo (2 años del giro)":"DEUDA VENCIDA"},{"Subdirección":"INVESTIGACIÓN APLICADA (SIA)","Programa":"FONDEF","Cuenta":"12106030222000","Nombre Cuenta":"DEUDORES CONCURSO IDEA FIC","Imputacion":"2403","financiamiento":"FIC","Beneficiario":"UNIVERSIDAD DE MAGALLANES","Público/Privado":"SI","Jurídico/Natural":"INSTITUCION PUBLICA","Proyecto":"ID23I10140","etapa":"","Fecha de Transferencia":"2024-10-18","Numero de Cuota":"C2-2","Monto de Transferencia":46575000.0,"Aplicaciones (Rendiciones)":30504512.0,"Reintegros":0.0,"Saldo":16070488.0,"Presentación Rendición":"8888-08-08","Vigente/Pendiente (según Rendición presentada)":"VIGENTE","Fecha Término de Proyecto":"2025-07-04","Estado según saldo (2 años del giro)":"DEUDA VENCIDA"},{"Subdirección":"INVESTIGACIÓN APLICADA (SIA)","Programa":"FONDEF","Cuenta":"12106030222000","Nombre Cuenta":"DEUDORES CONCURSO IDEA FIC","Imputacion":"2403","financiamiento":"FIC","Beneficiario":"UNIVERSIDAD DE MAGALLANES","Público/Privado":"SI","Jurídico/Natural":"INSTITUCION PUBLICA","Proyecto":"TA23I10057","etapa":"","Fecha de Transferencia":"2024-12-31","Numero de Cuota":"C2-4","Monto de Transferencia":164953125.0,"Aplicaciones (Rendiciones)":0.0,"Reintegros":0.0,"Saldo":164953125.0,"Presentación Rendición":"2027-12-21","Vigente/Pendiente (según Rendición presentada)":"VIGENTE","Fecha Término de Proyecto":"2027-11-07","Estado según saldo (2 años del giro)":"DEUDA VENCIDA"},{"Subdirección":"INVESTIGACIÓN APLICADA (SIA)","Programa":"FONDEF","Cuenta":"12106030223000","Nombre Cuenta":"CONCURSO IDEA ADULTO MAYOR","Imputacion":"2403","financiamiento":"ANID","Beneficiario":"UNIVERSIDAD DE MAGALLANES","Público/Privado":"SI","Jurídico/Natural":"INSTITUCION PUBLICA","Proyecto":"NAM24I0044","etapa":"","Fecha de Transferencia":"2024-10-18","Numero de Cuota":"C1-1","Monto de Transferencia":41200000.0,"Aplicaciones (Rendiciones)":0.0,"Reintegros":3828846.0,"Saldo":37371154.0,"Presentación Rendición":"8888-08-08","Vigente/Pendiente (según Rendición presentada)":"VIGENTE","Fecha Término de Proyecto":"2025-10-06","Estado según saldo (2 años del giro)":"DEUDA VENCIDA"},{"Subdirección":"INVESTIGACIÓN APLICADA (SIA)","Programa":"FONDEF","Cuenta":"12106030223000","Nombre Cuenta":"CONCURSO IDEA ADULTO MAYOR","Imputacion":"2403","financiamiento":"ANID","Beneficiario":"UNIVERSIDAD DE MAGALLANES","Público/Privado":"SI","Jurídico/Natural":"INSTITUCION PUBLICA","Proyecto":"NAM25I0040","etapa":"","Fecha de Transferencia":"2025-11-20","Numero de Cuota":"C1-1","Monto de Transferencia":43000000.0,"Aplicaciones (Rendiciones)":0.0,"Reintegros":0.0,"Saldo":43000000.0,"Presentación Rendición":"2026-12-20","Vigente/Pendiente (según Rendición presentada)":"VIGENTE","Fecha Término de Proyecto":"2026-09-29","Estado según saldo (2 años del giro)":"DEUDA SIN RETRASO"},{"Subdirección":"REDES, ESTRATEGIA Y CONOCIMIENTO (SREC)","Programa":"PCI","Cuenta":"12106030502000","Nombre Cuenta":"Deudores Fortalecimiento Centros Regionales","Imputacion":"2403","financiamiento":"ANID","Beneficiario":"UNIVERSIDAD DE MAGALLANES","Público/Privado":"SI","Jurídico/Natural":"INSTITUCION PUBLICA","Proyecto":"NELN250007","etapa":"","Fecha de Transferencia":"2025-12-30","Numero de Cuota":"C1-2","Monto de Transferencia":165102000.0,"Aplicaciones (Rendiciones)":0.0,"Reintegros":0.0,"Saldo":165102000.0,"Presentación Rendición":"2027-01-30","Vigente/Pendiente (según Rendición presentada)":"VIGENTE","Fecha Término de Proyecto":"2027-12-19","Estado según saldo (2 años del giro)":"DEUDA SIN RETRASO"},{"Subdirección":"REDES, ESTRATEGIA Y CONOCIMIENTO (SREC)","Programa":"PCI","Cuenta":"12106030505000","Nombre Cuenta":"Deudores Fondo Complementario","Imputacion":"2403","financiamiento":"ANID","Beneficiario":"UNIVERSIDAD DE MAGALLANES","Público/Privado":"SI","Jurídico/Natural":"INSTITUCION PUBLICA","Proyecto":"NEL123N0002","etapa":"","Fecha de Transferencia":"2024-11-25","Numero de Cuota":"C2-2","Monto de Transferencia":206288438.0,"Aplicaciones (Rendiciones)":50733146.0,"Reintegros":0.0,"Saldo":155555292.0,"Presentación Rendición":"8888-08-08","Vigente/Pendiente (según Rendición presentada)":"VIGENTE","Fecha Término de Proyecto":"2025-12-17","Estado según saldo (2 años del giro)":"DEUDA VENCIDA"},{"Subdirección":"REDES, ESTRATEGIA Y CONOCIMIENTO (SREC)","Programa":"PCI","Cuenta":"12106030506000","Nombre Cuenta":"Deudores Prorroga Cont. CR","Imputacion":"2403","financiamiento":"ANID","Beneficiario":"UNIVERSIDAD DE MAGALLANES","Público/Privado":"SI","Jurídico/Natural":"INSTITUCION PUBLICA","Proyecto":"NMCA250003","etapa":"","Fecha de Transferencia":"2026-05-29","Numero de Cuota":"C1","Monto de Transferencia":60500000.0,"Aplicaciones (Rendiciones)":0.0,"Reintegros":0.0,"Saldo":60500000.0,"Presentación Rendición":"2027-06-21","Vigente/Pendiente (según Rendición presentada)":"VIGENTE","Fecha Término de Proyecto":null,"Estado según saldo (2 años del giro)":"DEUDA SIN RETRASO"},{"Subdirección":"REDES, ESTRATEGIA Y CONOCIMIENTO (SREC)","Programa":"PCI","Cuenta":"12106030816000","Nombre Cuenta":"PLANES DE DESARROLLO PARA CENT","Imputacion":"2403","financiamiento":"ANID","Beneficiario":"UNIVERSIDAD DE MAGALLANES","Público/Privado":"SI","Jurídico/Natural":"INSTITUCION PUBLICA","Proyecto":"ACEH250007","etapa":"","Fecha de Transferencia":"2026-04-13","Numero de Cuota":"C1-1","Monto de Transferencia":190589996.0,"Aplicaciones (Rendiciones)":0.0,"Reintegros":0.0,"Saldo":190589996.0,"Presentación Rendición":"2027-01-22","Vigente/Pendiente (según Rendición presentada)":"VIGENTE","Fecha Término de Proyecto":"2026-12-31","Estado según saldo (2 años del giro)":"DEUDA SIN RETRASO"},{"Subdirección":"CAPITAL HUMANO (SCH)","Programa":"CHA","Cuenta":"12106030901000","Nombre Cuenta":"DEUDORES SUBV INST ACADEMIA","Imputacion":"2403","financiamiento":"ANID","Beneficiario":"UNIVERSIDAD DE MAGALLANES","Público/Privado":"SI","Jurídico/Natural":"INSTITUCION PUBLICA","Proyecto":"85240061","etapa":"","Fecha de Transferencia":"2025-08-21","Numero de Cuota":"C2-3","Monto de Transferencia":70433365.0,"Aplicaciones (Rendiciones)":21675498.0,"Reintegros":0.0,"Saldo":48757867.0,"Presentación Rendición":"2026-09-22","Vigente/Pendiente (según Rendición presentada)":"VIGENTE","Fecha Término de Proyecto":"2027-07-22","Estado según saldo (2 años del giro)":"DEUDA SIN RETRASO"},{"Subdirección":"CAPITAL HUMANO (SCH)","Programa":"CHA","Cuenta":"12106030901000","Nombre Cuenta":"DEUDORES SUBV INST ACADEMIA","Imputacion":"2403","financiamiento":"ANID","Beneficiario":"UNIVERSIDAD DE MAGALLANES","Público/Privado":"SI","Jurídico/Natural":"INSTITUCION PUBLICA","Proyecto":"85240139","etapa":"","Fecha de Transferencia":"2025-09-11","Numero de Cuota":"C2-3","Monto de Transferencia":73690240.0,"Aplicaciones (Rendiciones)":36412648.0,"Reintegros":0.0,"Saldo":37277592.0,"Presentación Rendición":"2027-08-23","Vigente/Pendiente (según Rendición presentada)":"VIGENTE","Fecha Término de Proyecto":"2027-07-22","Estado según saldo (2 años del giro)":"DEUDA SIN RETRASO"},{"Subdirección":"REDES, ESTRATEGIA Y CONOCIMIENTO (SREC)","Programa":"PCI","Cuenta":"12106031001000","Nombre Cuenta":"Proyectos Prog.Cientifco Nivel Inter.FIC","Imputacion":"2403","financiamiento":"FIC","Beneficiario":"UNIVERSIDAD DE MAGALLANES","Público/Privado":"SI","Jurídico/Natural":"INSTITUCION PUBLICA","Proyecto":"FOVI250112","etapa":"","Fecha de Transferencia":"2025-12-26","Numero de Cuota":"C1-1","Monto de Transferencia":29970000.0,"Aplicaciones (Rendiciones)":0.0,"Reintegros":0.0,"Saldo":29970000.0,"Presentación Rendición":"2027-01-25","Vigente/Pendiente (según Rendición presentada)":"VIGENTE","Fecha Término de Proyecto":"2027-01-05","Estado según saldo (2 años del giro)":"DEUDA SIN RETRASO"},{"Subdirección":"REDES, ESTRATEGIA Y CONOCIMIENTO (SREC)","Programa":"PCI","Cuenta":"12106031002000","Nombre Cuenta":"Proyectos Prog.Cientifco Nivel Internacional","Imputacion":"2403","financiamiento":"ANID","Beneficiario":"UNIVERSIDAD DE MAGALLANES","Público/Privado":"SI","Jurídico/Natural":"INSTITUCION PUBLICA","Proyecto":"FOVI240097","etapa":"","Fecha de Transferencia":"2024-11-25","Numero de Cuota":"C1-1","Monto de Transferencia":30000000.0,"Aplicaciones (Rendiciones)":10024514.0,"Reintegros":0.0,"Saldo":19975486.0,"Presentación Rendición":"8888-08-08","Vigente/Pendiente (según Rendición presentada)":"VIGENTE","Fecha Término de Proyecto":"2026-05-27","Estado según saldo (2 años del giro)":"DEUDA VENCIDA"},{"Subdirección":"REDES, ESTRATEGIA Y CONOCIMIENTO (SREC)","Programa":"PCI","Cuenta":"12106031701000","Nombre Cuenta":"APOYO INNOVA. E. SUP. INES I+D","Imputacion":"2403","financiamiento":"ANID","Beneficiario":"UNIVERSIDAD DE MAGALLANES","Público/Privado":"SI","Jurídico/Natural":"INSTITUCION PUBLICA","Proyecto":"INID220019","etapa":"","Fecha de Transferencia":"2024-12-30","Numero de Cuota":"C5-6","Monto de Transferencia":270166398.0,"Aplicaciones (Rendiciones)":179579456.0,"Reintegros":0.0,"Saldo":90586942.0,"Presentación Rendición":"8888-08-08","Vigente/Pendiente (según Rendición presentada)":"VIGENTE","Fecha Término de Proyecto":"2025-12-16","Estado según saldo (2 años del giro)":"DEUDA VENCIDA"},{"Subdirección":"REDES, ESTRATEGIA Y CONOCIMIENTO (SREC)","Programa":"PCI","Cuenta":"12106031703000","Nombre Cuenta":"APOYO INNOVA E.SUP. INES CIENC","Imputacion":"2403","financiamiento":"ANID","Beneficiario":"UNIVERSIDAD DE MAGALLANES","Público/Privado":"SI","Jurídico/Natural":"INSTITUCION PUBLICA","Proyecto":"INCA230007","etapa":"","Fecha de Transferencia":"2024-11-22","Numero de Cuota":"C3-6","Monto de Transferencia":88482150.0,"Aplicaciones (Rendiciones)":87370868.0,"Reintegros":0.0,"Saldo":1111282.0,"Presentación Rendición":"8888-08-08","Vigente/Pendiente (según Rendición presentada)":"VIGENTE","Fecha Término de Proyecto":"2026-03-25","Estado según saldo (2 años del giro)":"DEUDA VENCIDA"},{"Subdirección":"INVESTIGACIÓN APLICADA (SIA)","Programa":"FONDEF","Cuenta":"12106031801000","Nombre Cuenta":"DEUDORES INVESTIGACIÓN APLICADA (SIA)","Imputacion":"2403","financiamiento":"ANID","Beneficiario":"UNIVERSIDAD DE MAGALLANES","Público/Privado":"SI","Jurídico/Natural":"INSTITUCION PUBLICA","Proyecto":"OTL220014","etapa":"","Fecha de Transferencia":"2025-12-26","Numero de Cuota":"C4-4","Monto de Transferencia":30000000.0,"Aplicaciones (Rendiciones)":0.0,"Reintegros":0.0,"Saldo":30000000.0,"Presentación Rendición":"2026-11-20","Vigente/Pendiente (según Rendición presentada)":"VIGENTE","Fecha Término de Proyecto":"2026-10-25","Estado según saldo (2 años del giro)":"DEUDA SIN RETRASO"},{"Subdirección":"REDES, ESTRATEGIA Y CONOCIMIENTO (SREC)","Programa":"PCI","Cuenta":"12106031903000","Nombre Cuenta":"CONOCIMIENTO 2030","Imputacion":"2403","financiamiento":"CAPACIDADES TECNOLOGICAS","Beneficiario":"UNIVERSIDAD DE MAGALLANES","Público/Privado":"SI","Jurídico/Natural":"INSTITUCION PUBLICA","Proyecto":"CON24E20017","etapa":"","Fecha de Transferencia":"2025-12-11","Numero de Cuota":"C1-6","Monto de Transferencia":192222000.0,"Aplicaciones (Rendiciones)":0.0,"Reintegros":0.0,"Saldo":192222000.0,"Presentación Rendición":"2027-01-10","Vigente/Pendiente (según Rendición presentada)":"VIGENTE","Fecha Término de Proyecto":"2031-11-09","Estado según saldo (2 años del giro)":"DEUDA SIN RETRASO"},{"Subdirección":"INVESTIGACIÓN APLICADA (SIA)","Programa":"FONDEF","Cuenta":"12106032302000","Nombre Cuenta":"DEUDORES INNOVACION BASE CIENT","Imputacion":"2401","financiamiento":null,"Beneficiario":"UNIVERSIDAD DE MAGALLANES","Público/Privado":"SI","Jurídico/Natural":"INSTITUCION PUBLICA","Proyecto":"RP25I10001","etapa":"","Fecha de Transferencia":"2025-12-22","Numero de Cuota":"C1-1","Monto de Transferencia":29098000.0,"Aplicaciones (Rendiciones)":540000.0,"Reintegros":0.0,"Saldo":28558000.0,"Presentación Rendición":"2027-01-22","Vigente/Pendiente (según Rendición presentada)":"VIGENTE","Fecha Término de Proyecto":"2027-07-10","Estado según saldo (2 años del giro)":"DEUDA SIN RETRASO"},{"Subdirección":"REDES, ESTRATEGIA Y CONOCIMIENTO (SREC)","Programa":"PCI","Cuenta":"12106032401000","Nombre Cuenta":"DEUDORES FIU","Imputacion":"2403","financiamiento":"CAPACIDADES TECNOLOGICAS","Beneficiario":"UNIVERSIDAD DE MAGALLANES","Público/Privado":"SI","Jurídico/Natural":"INSTITUCION PUBLICA","Proyecto":"135815","etapa":"","Fecha de Transferencia":"2025-12-31","Numero de Cuota":"C1-11","Monto de Transferencia":260000000.0,"Aplicaciones (Rendiciones)":0.0,"Reintegros":0.0,"Saldo":260000000.0,"Presentación Rendición":"2027-01-30","Vigente/Pendiente (según Rendición presentada)":"VIGENTE","Fecha Término de Proyecto":"2035-12-31","Estado según saldo (2 años del giro)":"DEUDA SIN RETRASO"},{"Subdirección":"REDES, ESTRATEGIA Y CONOCIMIENTO (SREC)","Programa":"PCI","Cuenta":"12106041401000","Nombre Cuenta":"APOYO INNOVA EDUC. SUP I+D","Imputacion":"3303","financiamiento":"ANID","Beneficiario":"UNIVERSIDAD DE MAGALLANES","Público/Privado":"SI","Jurídico/Natural":"INSTITUCION PUBLICA","Proyecto":"INID220019","etapa":"","Fecha de Transferencia":"2024-12-30","Numero de Cuota":"C6-6","Monto de Transferencia":37083333.0,"Aplicaciones (Rendiciones)":32235523.0,"Reintegros":0.0,"Saldo":4847810.0,"Presentación Rendición":"8888-08-08","Vigente/Pendiente (según Rendición presentada)":"VIGENTE","Fecha Término de Proyecto":"2025-12-16","Estado según saldo (2 años del giro)":"DEUDA VENCIDA"},{"Subdirección":"REDES, ESTRATEGIA Y CONOCIMIENTO (SREC)","Programa":"PCI","Cuenta":"12106041403000","Nombre Cuenta":"APOYO INNO E. SUP.INES CIENCIA","Imputacion":"3303","financiamiento":"ANID","Beneficiario":"UNIVERSIDAD DE MAGALLANES","Público/Privado":"SI","Jurídico/Natural":"INSTITUCION PUBLICA","Proyecto":"INCA230007","etapa":"","Fecha de Transferencia":"2024-11-22","Numero de Cuota":"C4-6","Monto de Transferencia":2587500.0,"Aplicaciones (Rendiciones)":2414844.0,"Reintegros":0.0,"Saldo":172656.0,"Presentación Rendición":"8888-08-08","Vigente/Pendiente (según Rendición presentada)":"VIGENTE","Fecha Término de Proyecto":"2026-03-25","Estado según saldo (2 años del giro)":"DEUDA VENCIDA"},{"Subdirección":"CAPITAL HUMANO (SCH)","Programa":"CHA","Cuenta":"12402010000000","Nombre Cuenta":"Deudores Cobranza Adm. y recopilacion de antecedentes","Imputacion":"0","financiamiento":"ANID","Beneficiario":"UNIVERSIDAD DE MAGALLANES","Público/Privado":"SI","Jurídico/Natural":"INSTITUCION PUBLICA","Proyecto":"85220032","etapa":"","Fecha de Transferencia":"2022-12-31","Numero de Cuota":"1","Monto de Transferencia":51663334.0,"Aplicaciones (Rendiciones)":50280310.0,"Reintegros":0.0,"Saldo":1383024.0,"Presentación Rendición":"8888-08-08","Vigente/Pendiente (según Rendición presentada)":"VIGENTE","Fecha Término de Proyecto":"2026-01-31","Estado según saldo (2 años del giro)":"DEUDA MOROSA"},{"Subdirección":"CAPITAL HUMANO (SCH)","Programa":"CHA","Cuenta":"12402010000000","Nombre Cuenta":"Deudores Cobranza Adm. y recopilacion de antecedentes","Imputacion":"0","financiamiento":"ANID","Beneficiario":"UNIVERSIDAD DE MAGALLANES","Público/Privado":"SI","Jurídico/Natural":"INSTITUCION PUBLICA","Proyecto":"85220032","etapa":"","Fecha de Transferencia":"2023-11-23","Numero de Cuota":"2","Monto de Transferencia":51663334.0,"Aplicaciones (Rendiciones)":48730822.0,"Reintegros":0.0,"Saldo":2932512.0,"Presentación Rendición":"8888-08-08","Vigente/Pendiente (según Rendición presentada)":"VIGENTE","Fecha Término de Proyecto":"2026-01-31","Estado según saldo (2 años del giro)":"DEUDA MOROSA"},{"Subdirección":"CAPITAL HUMANO (SCH)","Programa":"CHA","Cuenta":"12402010000000","Nombre Cuenta":"Deudores Cobranza Adm. y recopilacion de antecedentes","Imputacion":"0","financiamiento":"ANID","Beneficiario":"UNIVERSIDAD DE MAGALLANES","Público/Privado":"SI","Jurídico/Natural":"INSTITUCION PUBLICA","Proyecto":"85220121","etapa":"","Fecha de Transferencia":"2023-12-22","Numero de Cuota":"2","Monto de Transferencia":66725515.0,"Aplicaciones (Rendiciones)":64759555.0,"Reintegros":0.0,"Saldo":1965960.0,"Presentación Rendición":"8888-08-08","Vigente/Pendiente (según Rendición presentada)":"VIGENTE","Fecha Término de Proyecto":"2026-09-28","Estado según saldo (2 años del giro)":"DEUDA MOROSA"},{"Subdirección":"CAPITAL HUMANO (SCH)","Programa":"CHA","Cuenta":"12402010000000","Nombre Cuenta":"Deudores Cobranza Adm. y recopilacion de antecedentes","Imputacion":"0","financiamiento":"ANID","Beneficiario":"UNIVERSIDAD DE MAGALLANES","Público/Privado":"SI","Jurídico/Natural":"INSTITUCION PUBLICA","Proyecto":"86220036","etapa":"","Fecha de Transferencia":"2023-06-07","Numero de Cuota":"1","Monto de Transferencia":86206120.0,"Aplicaciones (Rendiciones)":86143746.0,"Reintegros":0.0,"Saldo":62374.0,"Presentación Rendición":"8888-08-08","Vigente/Pendiente (según Rendición presentada)":"VIGENTE","Fecha Término de Proyecto":"2026-10-31","Estado según saldo (2 años del giro)":"DEUDA MOROSA"},{"Subdirección":"REDES, ESTRATEGIA Y CONOCIMIENTO (SREC)","Programa":"PCI","Cuenta":"12402010000000","Nombre Cuenta":"Deudores Cobranza Adm. y recopilacion de antecedentes","Imputacion":"0","financiamiento":"ANID","Beneficiario":"UNIVERSIDAD DE MAGALLANES","Público/Privado":"SI","Jurídico/Natural":"INSTITUCION PUBLICA","Proyecto":"INCA230007","etapa":"","Fecha de Transferencia":"2023-09-26","Numero de Cuota":"1","Monto de Transferencia":85490000.0,"Aplicaciones (Rendiciones)":83870724.0,"Reintegros":0.0,"Saldo":1619276.0,"Presentación Rendición":"8888-08-08","Vigente/Pendiente (según Rendición presentada)":"VIGENTE","Fecha Término de Proyecto":"2025-09-26","Estado según saldo (2 años del giro)":"DEUDA MOROSA"},{"Subdirección":"REDES, ESTRATEGIA Y CONOCIMIENTO (SREC)","Programa":"PCI","Cuenta":"12402010000000","Nombre Cuenta":"Deudores Cobranza Adm. y recopilacion de antecedentes","Imputacion":"0","financiamiento":"ANID","Beneficiario":"UNIVERSIDAD DE MAGALLANES","Público/Privado":"SI","Jurídico/Natural":"INSTITUCION PUBLICA","Proyecto":"INCA230007","etapa":"","Fecha de Transferencia":"2023-09-26","Numero de Cuota":"2","Monto de Transferencia":5000000.0,"Aplicaciones (Rendiciones)":2476671.0,"Reintegros":2500000.0,"Saldo":23329.0,"Presentación Rendición":"8888-08-08","Vigente/Pendiente (según Rendición presentada)":"VIGENTE","Fecha Término de Proyecto":"2025-09-26","Estado según saldo (2 años del giro)":"DEUDA MOROSA"},{"Subdirección":"REDES, ESTRATEGIA Y CONOCIMIENTO (SREC)","Programa":"PCI","Cuenta":"12402010000000","Nombre Cuenta":"Deudores Cobranza Adm. y recopilacion de antecedentes","Imputacion":"0","financiamiento":"ANID","Beneficiario":"UNIVERSIDAD DE MAGALLANES","Público/Privado":"SI","Jurídico/Natural":"INSTITUCION PUBLICA","Proyecto":"INID220019","etapa":"","Fecha de Transferencia":"2023-12-28","Numero de Cuota":"4","Monto de Transferencia":37083333.0,"Aplicaciones (Rendiciones)":30154045.0,"Reintegros":0.0,"Saldo":6929288.0,"Presentación Rendición":"8888-08-08","Vigente/Pendiente (según Rendición presentada)":"VIGENTE","Fecha Término de Proyecto":"2025-12-16","Estado según saldo (2 años del giro)":"DEUDA MOROSA"},{"Subdirección":"REDES, ESTRATEGIA Y CONOCIMIENTO (SREC)","Programa":"PCI","Cuenta":"12402010000000","Nombre Cuenta":"Deudores Cobranza Adm. y recopilacion de antecedentes","Imputacion":"0","financiamiento":"ANID","Beneficiario":"UNIVERSIDAD DE MAGALLANES","Público/Privado":"SI","Jurídico/Natural":"INSTITUCION PUBLICA","Proyecto":"INID220019","etapa":"","Fecha de Transferencia":"2022-12-16","Numero de Cuota":"1","Monto de Transferencia":270166398.0,"Aplicaciones (Rendiciones)":265941996.0,"Reintegros":0.0,"Saldo":4224402.0,"Presentación Rendición":"8888-08-08","Vigente/Pendiente (según Rendición presentada)":"VIGENTE","Fecha Término de Proyecto":"2025-12-16","Estado según saldo (2 años del giro)":"DEUDA MOROSA"},{"Subdirección":"REDES, ESTRATEGIA Y CONOCIMIENTO (SREC)","Programa":"PCI","Cuenta":"12402010000000","Nombre Cuenta":"Deudores Cobranza Adm. y recopilacion de antecedentes","Imputacion":"0","financiamiento":"ANID","Beneficiario":"UNIVERSIDAD DE MAGALLANES","Público/Privado":"SI","Jurídico/Natural":"INSTITUCION PUBLICA","Proyecto":"INID220019","etapa":"","Fecha de Transferencia":"2023-12-28","Numero de Cuota":"3","Monto de Transferencia":270166398.0,"Aplicaciones (Rendiciones)":238658593.0,"Reintegros":0.0,"Saldo":31507805.0,"Presentación Rendición":"8888-08-08","Vigente/Pendiente (según Rendición presentada)":"VIGENTE","Fecha Término de Proyecto":"2025-12-16","Estado según saldo (2 años del giro)":"DEUDA MOROSA"},{"Subdirección":"REDES, ESTRATEGIA Y CONOCIMIENTO (SREC)","Programa":"PCI","Cuenta":"12402010000000","Nombre Cuenta":"Deudores Cobranza Adm. y recopilacion de antecedentes","Imputacion":"0","financiamiento":"ANID","Beneficiario":"UNIVERSIDAD DE MAGALLANES","Público/Privado":"SI","Jurídico/Natural":"INSTITUCION PUBLICA","Proyecto":"NODO200004","etapa":"","Fecha de Transferencia":"2020-12-29","Numero de Cuota":"1","Monto de Transferencia":80000000.0,"Aplicaciones (Rendiciones)":32000000.0,"Reintegros":0.0,"Saldo":48000000.0,"Presentación Rendición":"8888-08-08","Vigente/Pendiente (según Rendición presentada)":"VIGENTE","Fecha Término de Proyecto":"2022-12-27","Estado según saldo (2 años del giro)":"DEUDA MOROSA"},{"Subdirección":"INVESTIGACIÓN APLICADA (SIA)","Programa":"FONDEF","Cuenta":"12402010000000","Nombre Cuenta":"Deudores Cobranza Adm. y recopilacion de antecedentes","Imputacion":"0","financiamiento":"ANID","Beneficiario":"UNIVERSIDAD DE MAGALLANES","Público/Privado":"SI","Jurídico/Natural":"INSTITUCION PUBLICA","Proyecto":"OTL220014","etapa":"","Fecha de Transferencia":"2023-12-27","Numero de Cuota":"2","Monto de Transferencia":60000000.0,"Aplicaciones (Rendiciones)":54167090.0,"Reintegros":0.0,"Saldo":5832910.0,"Presentación Rendición":"2026-11-20","Vigente/Pendiente (según Rendición presentada)":"VIGENTE","Fecha Término de Proyecto":"2026-10-25","Estado según saldo (2 años del giro)":"DEUDA MOROSA"},{"Subdirección":"INVESTIGACIÓN APLICADA (SIA)","Programa":"FONDEF","Cuenta":"12402010000000","Nombre Cuenta":"Deudores Cobranza Adm. y recopilacion de antecedentes","Imputacion":"0","financiamiento":"ANID","Beneficiario":"UNIVERSIDAD DE MAGALLANES","Público/Privado":"SI","Jurídico/Natural":"INSTITUCION PUBLICA","Proyecto":"TA23I10057","etapa":"","Fecha de Transferencia":"2023-10-26","Numero de Cuota":"1","Monto de Transferencia":159375000.0,"Aplicaciones (Rendiciones)":106660421.0,"Reintegros":0.0,"Saldo":52714579.0,"Presentación Rendición":"2027-12-22","Vigente/Pendiente (según Rendición presentada)":"VIGENTE","Fecha Término de Proyecto":"2027-11-07","Estado según saldo (2 años del giro)":"DEUDA MOROSA"},{"Subdirección":"REDES, ESTRATEGIA Y CONOCIMIENTO (SREC)","Programa":"PCI","Cuenta":"12402020000000","Nombre Cuenta":"Deudores de cobranza prejudicial","Imputacion":"0","financiamiento":"ANID","Beneficiario":"UNIVERSIDAD DE MAGALLANES","Público/Privado":"SI","Jurídico/Natural":"INSTITUCION PUBLICA","Proyecto":"MEC80190113","etapa":"","Fecha de Transferencia":"2019-12-31","Numero de Cuota":"1","Monto de Transferencia":32000000.0,"Aplicaciones (Rendiciones)":11553099.0,"Reintegros":0.0,"Saldo":20446901.0,"Presentación Rendición":"8888-08-08","Vigente/Pendiente (según Rendición presentada)":"VIGENTE","Fecha Término de Proyecto":"2022-08-31","Estado según saldo (2 años del giro)":"DEUDA MOROSA"},{"Subdirección":"REDES, ESTRATEGIA Y CONOCIMIENTO (SREC)","Programa":"PAI","Cuenta":"12402020000000","Nombre Cuenta":"Deudores de cobranza prejudicial","Imputacion":"0","financiamiento":"ANID","Beneficiario":"UNIVERSIDAD DE MAGALLANES","Público/Privado":"SI","Jurídico/Natural":"INSTITUCION PUBLICA","Proyecto":"PAI77180002","etapa":"","Fecha de Transferencia":"2020-10-19","Numero de Cuota":"3","Monto de Transferencia":68080000.0,"Aplicaciones (Rendiciones)":67464631.0,"Reintegros":0.0,"Saldo":615369.0,"Presentación Rendición":"8888-08-08","Vigente/Pendiente (según Rendición presentada)":"VIGENTE","Fecha Término de Proyecto":"2024-01-14","Estado según saldo (2 años del giro)":"DEUDA MOROSA"},{"Subdirección":"REDES, ESTRATEGIA Y CONOCIMIENTO (SREC)","Programa":"PAI","Cuenta":"12402020000000","Nombre Cuenta":"Deudores de cobranza prejudicial","Imputacion":"0","financiamiento":"ANID","Beneficiario":"UNIVERSIDAD DE MAGALLANES","Público/Privado":"SI","Jurídico/Natural":"INSTITUCION PUBLICA","Proyecto":"PAI79170119","etapa":"","Fecha de Transferencia":"2019-12-30","Numero de Cuota":"2","Monto de Transferencia":22320000.0,"Aplicaciones (Rendiciones)":20739300.0,"Reintegros":0.0,"Saldo":1580700.0,"Presentación Rendición":"8888-08-08","Vigente/Pendiente (según Rendición presentada)":"VIGENTE","Fecha Término de Proyecto":"2021-03-31","Estado según saldo (2 años del giro)":"DEUDA MOROSA"},{"Subdirección":"REDES, ESTRATEGIA Y CONOCIMIENTO (SREC)","Programa":"PAI","Cuenta":"12402020000000","Nombre Cuenta":"Deudores de cobranza prejudicial","Imputacion":"0","financiamiento":"ANID","Beneficiario":"UNIVERSIDAD DE MAGALLANES","Público/Privado":"SI","Jurídico/Natural":"INSTITUCION PUBLICA","Proyecto":"PAI79170119","etapa":"","Fecha de Transferencia":"2017-12-15","Numero de Cuota":"1","Monto de Transferencia":42320000.0,"Aplicaciones (Rendiciones)":39788972.0,"Reintegros":0.0,"Saldo":2531028.0,"Presentación Rendición":"8888-08-08","Vigente/Pendiente (según Rendición presentada)":"VIGENTE","Fecha Término de Proyecto":"2021-03-31","Estado según saldo (2 años del giro)":"DEUDA MOROSA"},{"Subdirección":"REDES, ESTRATEGIA Y CONOCIMIENTO (SREC)","Programa":"PAI","Cuenta":"12402020000000","Nombre Cuenta":"Deudores de cobranza prejudicial","Imputacion":"0","financiamiento":"ANID","Beneficiario":"UNIVERSIDAD DE MAGALLANES","Público/Privado":"SI","Jurídico/Natural":"INSTITUCION PUBLICA","Proyecto":"PAI79170119","etapa":"","Fecha de Transferencia":"2019-12-30","Numero de Cuota":"3","Monto de Transferencia":22320000.0,"Aplicaciones (Rendiciones)":17670194.0,"Reintegros":0.0,"Saldo":4649806.0,"Presentación Rendición":"8888-08-08","Vigente/Pendiente (según Rendición presentada)":"VIGENTE","Fecha Término de Proyecto":"2021-03-31","Estado según saldo (2 años del giro)":"DEUDA MOROSA"}]}